[{"_path":"/examples/element-plus","_dir":"examples","_draft":false,"_partial":false,"_locale":"","title":"Element Plus","description":"Using Vue3 Mobile Table with Element Plus tables","icon":"lucide:table","_type":"markdown","_id":"content:3.examples:1.element-plus.md","_source":"content","_file":"3.examples/1.element-plus.md","_stem":"3.examples/1.element-plus","_extension":"md"},{"_path":"/examples/naive-ui","_dir":"examples","_draft":false,"_partial":false,"_locale":"","title":"Naive UI","description":"Using Vue3 Mobile Table with Naive UI tables","icon":"lucide:table","_type":"markdown","_id":"content:3.examples:3.naive-ui.md","_source":"content","_file":"3.examples/3.naive-ui.md","_stem":"3.examples/3.naive-ui","_extension":"md"}]