{"_path":"/zh/guide/configuration","_dir":"guide","_draft":false,"_partial":false,"_locale":"","title":"使用指南","description":null,"icon":"lucide:settings","body":{"type":"root","children":[{"type":"element","tag":"p","props":{},"children":[{"type":"text","value":"本页介绍 "},{"type":"element","tag":"code","props":{"className":[]},"children":[{"type":"text","value":"v-table-touch-scroll"}]},{"type":"text","value":" 指令的常见用法。完整的配置项和类型定义请参考 "},{"type":"element","tag":"a","props":{"href":"/zh/api/parameters"},"children":[{"type":"text","value":"API"}]},{"type":"text","value":"。"}]},{"type":"element","tag":"h2","props":{"id":"安装"},"children":[{"type":"text","value":"安装"}]},{"type":"element","tag":"code-group","props":{},"children":[{"type":"element","tag":"pre","props":{"className":"language-bash shiki shiki-themes github-light github-dark","code":"npm install vue-table-touch-scroll\n","filename":"npm","language":"bash","meta":"","style":""},"children":[{"type":"element","tag":"code","props":{"__ignoreMap":""},"children":[{"type":"element","tag":"span","props":{"class":"line","line":1},"children":[{"type":"element","tag":"span","props":{"style":"--shiki-default:#6F42C1;--shiki-dark:#B392F0"},"children":[{"type":"text","value":"npm"}]},{"type":"element","tag":"span","props":{"style":"--shiki-default:#032F62;--shiki-dark:#9ECBFF"},"children":[{"type":"text","value":" install"}]},{"type":"element","tag":"span","props":{"style":"--shiki-default:#032F62;--shiki-dark:#9ECBFF"},"children":[{"type":"text","value":" vue-table-touch-scroll\n"}]}]}]}]},{"type":"element","tag":"pre","props":{"className":"language-bash shiki shiki-themes github-light github-dark","code":"yarn add vue-table-touch-scroll\n","filename":"yarn","language":"bash","meta":"","style":""},"children":[{"type":"element","tag":"code","props":{"__ignoreMap":""},"children":[{"type":"element","tag":"span","props":{"class":"line","line":1},"children":[{"type":"element","tag":"span","props":{"style":"--shiki-default:#6F42C1;--shiki-dark:#B392F0"},"children":[{"type":"text","value":"yarn"}]},{"type":"element","tag":"span","props":{"style":"--shiki-default:#032F62;--shiki-dark:#9ECBFF"},"children":[{"type":"text","value":" add"}]},{"type":"element","tag":"span","props":{"style":"--shiki-default:#032F62;--shiki-dark:#9ECBFF"},"children":[{"type":"text","value":" vue-table-touch-scroll\n"}]}]}]}]},{"type":"element","tag":"pre","props":{"className":"language-bash shiki shiki-themes github-light github-dark","code":"pnpm add vue-table-touch-scroll\n","filename":"pnpm","language":"bash","meta":"","style":""},"children":[{"type":"element","tag":"code","props":{"__ignoreMap":""},"children":[{"type":"element","tag":"span","props":{"class":"line","line":1},"children":[{"type":"element","tag":"span","props":{"style":"--shiki-default:#6F42C1;--shiki-dark:#B392F0"},"children":[{"type":"text","value":"pnpm"}]},{"type":"element","tag":"span","props":{"style":"--shiki-default:#032F62;--shiki-dark:#9ECBFF"},"children":[{"type":"text","value":" add"}]},{"type":"element","tag":"span","props":{"style":"--shiki-default:#032F62;--shiki-dark:#9ECBFF"},"children":[{"type":"text","value":" vue-table-touch-scroll\n"}]}]}]}]}]},{"type":"element","tag":"h2","props":{"id":"全局注册"},"children":[{"type":"text","value":"全局注册"}]},{"type":"element","tag":"pre","props":{"className":"language-ts shiki shiki-themes github-light github-dark","code":"import { createApp } from 'vue'\nimport App from './App.vue'\nimport VueTableTouchScroll from 'vue-table-touch-scroll'\n\nconst app = createApp(App)\napp.use(VueTableTouchScroll)\napp.mount('#app')\n","filename":"main.ts","language":"ts","meta":"","style":""},"children":[{"type":"element","tag":"code","props":{"__ignoreMap":""},"children":[{"type":"element","tag":"span","props":{"class":"line","line":1},"children":[{"type":"element","tag":"span","props":{"style":"--shiki-default:#D73A49;--shiki-dark:#F97583"},"children":[{"type":"text","value":"import"}]},{"type":"element","tag":"span","props":{"style":"--shiki-default:#24292E;--shiki-dark:#E1E4E8"},"children":[{"type":"text","value":" { createApp } "}]},{"type":"element","tag":"span","props":{"style":"--shiki-default:#D73A49;--shiki-dark:#F97583"},"children":[{"type":"text","value":"from"}]},{"type":"element","tag":"span","props":{"style":"--shiki-default:#032F62;--shiki-dark:#9ECBFF"},"children":[{"type":"text","value":" 'vue'\n"}]}]},{"type":"element","tag":"span","props":{"class":"line","line":2},"children":[{"type":"element","tag":"span","props":{"style":"--shiki-default:#D73A49;--shiki-dark:#F97583"},"children":[{"type":"text","value":"import"}]},{"type":"element","tag":"span","props":{"style":"--shiki-default:#24292E;--shiki-dark:#E1E4E8"},"children":[{"type":"text","value":" App "}]},{"type":"element","tag":"span","props":{"style":"--shiki-default:#D73A49;--shiki-dark:#F97583"},"children":[{"type":"text","value":"from"}]},{"type":"element","tag":"span","props":{"style":"--shiki-default:#032F62;--shiki-dark:#9ECBFF"},"children":[{"type":"text","value":" './App.vue'\n"}]}]},{"type":"element","tag":"span","props":{"class":"line","line":3},"children":[{"type":"element","tag":"span","props":{"style":"--shiki-default:#D73A49;--shiki-dark:#F97583"},"children":[{"type":"text","value":"import"}]},{"type":"element","tag":"span","props":{"style":"--shiki-default:#24292E;--shiki-dark:#E1E4E8"},"children":[{"type":"text","value":" VueTableTouchScroll "}]},{"type":"element","tag":"span","props":{"style":"--shiki-default:#D73A49;--shiki-dark:#F97583"},"children":[{"type":"text","value":"from"}]},{"type":"element","tag":"span","props":{"style":"--shiki-default:#032F62;--shiki-dark:#9ECBFF"},"children":[{"type":"text","value":" 'vue-table-touch-scroll'\n"}]}]},{"type":"element","tag":"span","props":{"class":"line","line":4},"children":[{"type":"element","tag":"span","props":{"emptyLinePlaceholder":true},"children":[{"type":"text","value":"\n"}]}]},{"type":"element","tag":"span","props":{"class":"line","line":5},"children":[{"type":"element","tag":"span","props":{"style":"--shiki-default:#D73A49;--shiki-dark:#F97583"},"children":[{"type":"text","value":"const"}]},{"type":"element","tag":"span","props":{"style":"--shiki-default:#005CC5;--shiki-dark:#79B8FF"},"children":[{"type":"text","value":" app"}]},{"type":"element","tag":"span","props":{"style":"--shiki-default:#D73A49;--shiki-dark:#F97583"},"children":[{"type":"text","value":" ="}]},{"type":"element","tag":"span","props":{"style":"--shiki-default:#6F42C1;--shiki-dark:#B392F0"},"children":[{"type":"text","value":" createApp"}]},{"type":"element","tag":"span","props":{"style":"--shiki-default:#24292E;--shiki-dark:#E1E4E8"},"children":[{"type":"text","value":"(App)\n"}]}]},{"type":"element","tag":"span","props":{"class":"line","line":6},"children":[{"type":"element","tag":"span","props":{"style":"--shiki-default:#24292E;--shiki-dark:#E1E4E8"},"children":[{"type":"text","value":"app."}]},{"type":"element","tag":"span","props":{"style":"--shiki-default:#6F42C1;--shiki-dark:#B392F0"},"children":[{"type":"text","value":"use"}]},{"type":"element","tag":"span","props":{"style":"--shiki-default:#24292E;--shiki-dark:#E1E4E8"},"children":[{"type":"text","value":"(VueTableTouchScroll)\n"}]}]},{"type":"element","tag":"span","props":{"class":"line","line":7},"children":[{"type":"element","tag":"span","props":{"style":"--shiki-default:#24292E;--shiki-dark:#E1E4E8"},"children":[{"type":"text","value":"app."}]},{"type":"element","tag":"span","props":{"style":"--shiki-default:#6F42C1;--shiki-dark:#B392F0"},"children":[{"type":"text","value":"mount"}]},{"type":"element","tag":"span","props":{"style":"--shiki-default:#24292E;--shiki-dark:#E1E4E8"},"children":[{"type":"text","value":"("}]},{"type":"element","tag":"span","props":{"style":"--shiki-default:#032F62;--shiki-dark:#9ECBFF"},"children":[{"type":"text","value":"'#app'"}]},{"type":"element","tag":"span","props":{"style":"--shiki-default:#24292E;--shiki-dark:#E1E4E8"},"children":[{"type":"text","value":")\n"}]}]}]}]},{"type":"element","tag":"h2","props":{"id":"局部注册"},"children":[{"type":"text","value":"局部注册"}]},{"type":"element","tag":"p","props":{},"children":[{"type":"text","value":"如果不需要全局注册，可以在组件中直接导入指令："}]},{"type":"element","tag":"pre","props":{"className":"language-vue shiki shiki-themes github-light github-dark","code":"<script setup lang=\"ts\">\nimport { vTableTouchScroll } from 'vue-table-touch-scroll'\n</script>\n\n<template>\n  <div v-table-touch-scroll=\"{ preset: 'element-plus' }\">\n    <el-table :data=\"tableData\" />\n  </div>\n</template>\n","language":"vue","meta":"","style":""},"children":[{"type":"element","tag":"code","props":{"__ignoreMap":""},"children":[{"type":"element","tag":"span","props":{"class":"line","line":1},"children":[{"type":"element","tag":"span","props":{"style":"--shiki-default:#24292E;--shiki-dark:#E1E4E8"},"children":[{"type":"text","value":"<"}]},{"type":"element","tag":"span","props":{"style":"--shiki-default:#22863A;--shiki-dark:#85E89D"},"children":[{"type":"text","value":"script"}]},{"type":"element","tag":"span","props":{"style":"--shiki-default:#6F42C1;--shiki-dark:#B392F0"},"children":[{"type":"text","value":" setup"}]},{"type":"element","tag":"span","props":{"style":"--shiki-default:#6F42C1;--shiki-dark:#B392F0"},"children":[{"type":"text","value":" lang"}]},{"type":"element","tag":"span","props":{"style":"--shiki-default:#24292E;--shiki-dark:#E1E4E8"},"children":[{"type":"text","value":"="}]},{"type":"element","tag":"span","props":{"style":"--shiki-default:#032F62;--shiki-dark:#9ECBFF"},"children":[{"type":"text","value":"\"ts\""}]},{"type":"element","tag":"span","props":{"style":"--shiki-default:#24292E;--shiki-dark:#E1E4E8"},"children":[{"type":"text","value":">\n"}]}]},{"type":"element","tag":"span","props":{"class":"line","line":2},"children":[{"type":"element","tag":"span","props":{"style":"--shiki-default:#D73A49;--shiki-dark:#F97583"},"children":[{"type":"text","value":"import"}]},{"type":"element","tag":"span","props":{"style":"--shiki-default:#24292E;--shiki-dark:#E1E4E8"},"children":[{"type":"text","value":" { vTableTouchScroll } "}]},{"type":"element","tag":"span","props":{"style":"--shiki-default:#D73A49;--shiki-dark:#F97583"},"children":[{"type":"text","value":"from"}]},{"type":"element","tag":"span","props":{"style":"--shiki-default:#032F62;--shiki-dark:#9ECBFF"},"children":[{"type":"text","value":" 'vue-table-touch-scroll'\n"}]}]},{"type":"element","tag":"span","props":{"class":"line","line":3},"children":[{"type":"element","tag":"span","props":{"style":"--shiki-default:#24292E;--shiki-dark:#E1E4E8"},"children":[{"type":"text","value":"</"}]},{"type":"element","tag":"span","props":{"style":"--shiki-default:#22863A;--shiki-dark:#85E89D"},"children":[{"type":"text","value":"script"}]},{"type":"element","tag":"span","props":{"style":"--shiki-default:#24292E;--shiki-dark:#E1E4E8"},"children":[{"type":"text","value":">\n"}]}]},{"type":"element","tag":"span","props":{"class":"line","line":4},"children":[{"type":"element","tag":"span","props":{"emptyLinePlaceholder":true},"children":[{"type":"text","value":"\n"}]}]},{"type":"element","tag":"span","props":{"class":"line","line":5},"children":[{"type":"element","tag":"span","props":{"style":"--shiki-default:#24292E;--shiki-dark:#E1E4E8"},"children":[{"type":"text","value":"<"}]},{"type":"element","tag":"span","props":{"style":"--shiki-default:#22863A;--shiki-dark:#85E89D"},"children":[{"type":"text","value":"template"}]},{"type":"element","tag":"span","props":{"style":"--shiki-default:#24292E;--shiki-dark:#E1E4E8"},"children":[{"type":"text","value":">\n"}]}]},{"type":"element","tag":"span","props":{"class":"line","line":6},"children":[{"type":"element","tag":"span","props":{"style":"--shiki-default:#24292E;--shiki-dark:#E1E4E8"},"children":[{"type":"text","value":"  <"}]},{"type":"element","tag":"span","props":{"style":"--shiki-default:#22863A;--shiki-dark:#85E89D"},"children":[{"type":"text","value":"div"}]},{"type":"element","tag":"span","props":{"style":"--shiki-default:#6F42C1;--shiki-dark:#B392F0"},"children":[{"type":"text","value":" v-table-touch-scroll"}]},{"type":"element","tag":"span","props":{"style":"--shiki-default:#24292E;--shiki-dark:#E1E4E8"},"children":[{"type":"text","value":"="}]},{"type":"element","tag":"span","props":{"style":"--shiki-default:#032F62;--shiki-dark:#9ECBFF"},"children":[{"type":"text","value":"\"{ preset: 'element-plus' }\""}]},{"type":"element","tag":"span","props":{"style":"--shiki-default:#24292E;--shiki-dark:#E1E4E8"},"children":[{"type":"text","value":">\n"}]}]},{"type":"element","tag":"span","props":{"class":"line","line":7},"children":[{"type":"element","tag":"span","props":{"style":"--shiki-default:#24292E;--shiki-dark:#E1E4E8"},"children":[{"type":"text","value":"    <"}]},{"type":"element","tag":"span","props":{"style":"--shiki-default:#22863A;--shiki-dark:#85E89D"},"children":[{"type":"text","value":"el-table"}]},{"type":"element","tag":"span","props":{"style":"--shiki-default:#6F42C1;--shiki-dark:#B392F0"},"children":[{"type":"text","value":" :data"}]},{"type":"element","tag":"span","props":{"style":"--shiki-default:#24292E;--shiki-dark:#E1E4E8"},"children":[{"type":"text","value":"="}]},{"type":"element","tag":"span","props":{"style":"--shiki-default:#032F62;--shiki-dark:#9ECBFF"},"children":[{"type":"text","value":"\"tableData\""}]},{"type":"element","tag":"span","props":{"style":"--shiki-default:#24292E;--shiki-dark:#E1E4E8"},"children":[{"type":"text","value":" />\n"}]}]},{"type":"element","tag":"span","props":{"class":"line","line":8},"children":[{"type":"element","tag":"span","props":{"style":"--shiki-default:#24292E;--shiki-dark:#E1E4E8"},"children":[{"type":"text","value":"  </"}]},{"type":"element","tag":"span","props":{"style":"--shiki-default:#22863A;--shiki-dark:#85E89D"},"children":[{"type":"text","value":"div"}]},{"type":"element","tag":"span","props":{"style":"--shiki-default:#24292E;--shiki-dark:#E1E4E8"},"children":[{"type":"text","value":">\n"}]}]},{"type":"element","tag":"span","props":{"class":"line","line":9},"children":[{"type":"element","tag":"span","props":{"style":"--shiki-default:#24292E;--shiki-dark:#E1E4E8"},"children":[{"type":"text","value":"</"}]},{"type":"element","tag":"span","props":{"style":"--shiki-default:#22863A;--shiki-dark:#85E89D"},"children":[{"type":"text","value":"template"}]},{"type":"element","tag":"span","props":{"style":"--shiki-default:#24292E;--shiki-dark:#E1E4E8"},"children":[{"type":"text","value":">\n"}]}]}]}]},{"type":"element","tag":"h2","props":{"id":"在模板中使用"},"children":[{"type":"text","value":"在模板中使用"}]},{"type":"element","tag":"pre","props":{"className":"language-vue shiki shiki-themes github-light github-dark","code":"<template>\n  <div v-table-touch-scroll=\"{ preset: 'element-plus' }\">\n    <el-table :data=\"tableData\">\n      <el-table-column prop=\"name\" label=\"Name\" />\n      <el-table-column prop=\"age\" label=\"Age\" />\n      <el-table-column prop=\"address\" label=\"Address\" />\n    </el-table>\n  </div>\n</template>\n","filename":"MyComponent.vue","language":"vue","meta":"","style":""},"children":[{"type":"element","tag":"code","props":{"__ignoreMap":""},"children":[{"type":"element","tag":"span","props":{"class":"line","line":1},"children":[{"type":"element","tag":"span","props":{"style":"--shiki-default:#24292E;--shiki-dark:#E1E4E8"},"children":[{"type":"text","value":"<"}]},{"type":"element","tag":"span","props":{"style":"--shiki-default:#22863A;--shiki-dark:#85E89D"},"children":[{"type":"text","value":"template"}]},{"type":"element","tag":"span","props":{"style":"--shiki-default:#24292E;--shiki-dark:#E1E4E8"},"children":[{"type":"text","value":">\n"}]}]},{"type":"element","tag":"span","props":{"class":"line","line":2},"children":[{"type":"element","tag":"span","props":{"style":"--shiki-default:#24292E;--shiki-dark:#E1E4E8"},"children":[{"type":"text","value":"  <"}]},{"type":"element","tag":"span","props":{"style":"--shiki-default:#22863A;--shiki-dark:#85E89D"},"children":[{"type":"text","value":"div"}]},{"type":"element","tag":"span","props":{"style":"--shiki-default:#6F42C1;--shiki-dark:#B392F0"},"children":[{"type":"text","value":" v-table-touch-scroll"}]},{"type":"element","tag":"span","props":{"style":"--shiki-default:#24292E;--shiki-dark:#E1E4E8"},"children":[{"type":"text","value":"="}]},{"type":"element","tag":"span","props":{"style":"--shiki-default:#032F62;--shiki-dark:#9ECBFF"},"children":[{"type":"text","value":"\"{ preset: 'element-plus' }\""}]},{"type":"element","tag":"span","props":{"style":"--shiki-default:#24292E;--shiki-dark:#E1E4E8"},"children":[{"type":"text","value":">\n"}]}]},{"type":"element","tag":"span","props":{"class":"line","line":3},"children":[{"type":"element","tag":"span","props":{"style":"--shiki-default:#24292E;--shiki-dark:#E1E4E8"},"children":[{"type":"text","value":"    <"}]},{"type":"element","tag":"span","props":{"style":"--shiki-default:#22863A;--shiki-dark:#85E89D"},"children":[{"type":"text","value":"el-table"}]},{"type":"element","tag":"span","props":{"style":"--shiki-default:#6F42C1;--shiki-dark:#B392F0"},"children":[{"type":"text","value":" :data"}]},{"type":"element","tag":"span","props":{"style":"--shiki-default:#24292E;--shiki-dark:#E1E4E8"},"children":[{"type":"text","value":"="}]},{"type":"element","tag":"span","props":{"style":"--shiki-default:#032F62;--shiki-dark:#9ECBFF"},"children":[{"type":"text","value":"\"tableData\""}]},{"type":"element","tag":"span","props":{"style":"--shiki-default:#24292E;--shiki-dark:#E1E4E8"},"children":[{"type":"text","value":">\n"}]}]},{"type":"element","tag":"span","props":{"class":"line","line":4},"children":[{"type":"element","tag":"span","props":{"style":"--shiki-default:#24292E;--shiki-dark:#E1E4E8"},"children":[{"type":"text","value":"      <"}]},{"type":"element","tag":"span","props":{"style":"--shiki-default:#22863A;--shiki-dark:#85E89D"},"children":[{"type":"text","value":"el-table-column"}]},{"type":"element","tag":"span","props":{"style":"--shiki-default:#6F42C1;--shiki-dark:#B392F0"},"children":[{"type":"text","value":" prop"}]},{"type":"element","tag":"span","props":{"style":"--shiki-default:#24292E;--shiki-dark:#E1E4E8"},"children":[{"type":"text","value":"="}]},{"type":"element","tag":"span","props":{"style":"--shiki-default:#032F62;--shiki-dark:#9ECBFF"},"children":[{"type":"text","value":"\"name\""}]},{"type":"element","tag":"span","props":{"style":"--shiki-default:#6F42C1;--shiki-dark:#B392F0"},"children":[{"type":"text","value":" label"}]},{"type":"element","tag":"span","props":{"style":"--shiki-default:#24292E;--shiki-dark:#E1E4E8"},"children":[{"type":"text","value":"="}]},{"type":"element","tag":"span","props":{"style":"--shiki-default:#032F62;--shiki-dark:#9ECBFF"},"children":[{"type":"text","value":"\"Name\""}]},{"type":"element","tag":"span","props":{"style":"--shiki-default:#24292E;--shiki-dark:#E1E4E8"},"children":[{"type":"text","value":" />\n"}]}]},{"type":"element","tag":"span","props":{"class":"line","line":5},"children":[{"type":"element","tag":"span","props":{"style":"--shiki-default:#24292E;--shiki-dark:#E1E4E8"},"children":[{"type":"text","value":"      <"}]},{"type":"element","tag":"span","props":{"style":"--shiki-default:#22863A;--shiki-dark:#85E89D"},"children":[{"type":"text","value":"el-table-column"}]},{"type":"element","tag":"span","props":{"style":"--shiki-default:#6F42C1;--shiki-dark:#B392F0"},"children":[{"type":"text","value":" prop"}]},{"type":"element","tag":"span","props":{"style":"--shiki-default:#24292E;--shiki-dark:#E1E4E8"},"children":[{"type":"text","value":"="}]},{"type":"element","tag":"span","props":{"style":"--shiki-default:#032F62;--shiki-dark:#9ECBFF"},"children":[{"type":"text","value":"\"age\""}]},{"type":"element","tag":"span","props":{"style":"--shiki-default:#6F42C1;--shiki-dark:#B392F0"},"children":[{"type":"text","value":" label"}]},{"type":"element","tag":"span","props":{"style":"--shiki-default:#24292E;--shiki-dark:#E1E4E8"},"children":[{"type":"text","value":"="}]},{"type":"element","tag":"span","props":{"style":"--shiki-default:#032F62;--shiki-dark:#9ECBFF"},"children":[{"type":"text","value":"\"Age\""}]},{"type":"element","tag":"span","props":{"style":"--shiki-default:#24292E;--shiki-dark:#E1E4E8"},"children":[{"type":"text","value":" />\n"}]}]},{"type":"element","tag":"span","props":{"class":"line","line":6},"children":[{"type":"element","tag":"span","props":{"style":"--shiki-default:#24292E;--shiki-dark:#E1E4E8"},"children":[{"type":"text","value":"      <"}]},{"type":"element","tag":"span","props":{"style":"--shiki-default:#22863A;--shiki-dark:#85E89D"},"children":[{"type":"text","value":"el-table-column"}]},{"type":"element","tag":"span","props":{"style":"--shiki-default:#6F42C1;--shiki-dark:#B392F0"},"children":[{"type":"text","value":" prop"}]},{"type":"element","tag":"span","props":{"style":"--shiki-default:#24292E;--shiki-dark:#E1E4E8"},"children":[{"type":"text","value":"="}]},{"type":"element","tag":"span","props":{"style":"--shiki-default:#032F62;--shiki-dark:#9ECBFF"},"children":[{"type":"text","value":"\"address\""}]},{"type":"element","tag":"span","props":{"style":"--shiki-default:#6F42C1;--shiki-dark:#B392F0"},"children":[{"type":"text","value":" label"}]},{"type":"element","tag":"span","props":{"style":"--shiki-default:#24292E;--shiki-dark:#E1E4E8"},"children":[{"type":"text","value":"="}]},{"type":"element","tag":"span","props":{"style":"--shiki-default:#032F62;--shiki-dark:#9ECBFF"},"children":[{"type":"text","value":"\"Address\""}]},{"type":"element","tag":"span","props":{"style":"--shiki-default:#24292E;--shiki-dark:#E1E4E8"},"children":[{"type":"text","value":" />\n"}]}]},{"type":"element","tag":"span","props":{"class":"line","line":7},"children":[{"type":"element","tag":"span","props":{"style":"--shiki-default:#24292E;--shiki-dark:#E1E4E8"},"children":[{"type":"text","value":"    </"}]},{"type":"element","tag":"span","props":{"style":"--shiki-default:#22863A;--shiki-dark:#85E89D"},"children":[{"type":"text","value":"el-table"}]},{"type":"element","tag":"span","props":{"style":"--shiki-default:#24292E;--shiki-dark:#E1E4E8"},"children":[{"type":"text","value":">\n"}]}]},{"type":"element","tag":"span","props":{"class":"line","line":8},"children":[{"type":"element","tag":"span","props":{"style":"--shiki-default:#24292E;--shiki-dark:#E1E4E8"},"children":[{"type":"text","value":"  </"}]},{"type":"element","tag":"span","props":{"style":"--shiki-default:#22863A;--shiki-dark:#85E89D"},"children":[{"type":"text","value":"div"}]},{"type":"element","tag":"span","props":{"style":"--shiki-default:#24292E;--shiki-dark:#E1E4E8"},"children":[{"type":"text","value":">\n"}]}]},{"type":"element","tag":"span","props":{"class":"line","line":9},"children":[{"type":"element","tag":"span","props":{"style":"--shiki-default:#24292E;--shiki-dark:#E1E4E8"},"children":[{"type":"text","value":"</"}]},{"type":"element","tag":"span","props":{"style":"--shiki-default:#22863A;--shiki-dark:#85E89D"},"children":[{"type":"text","value":"template"}]},{"type":"element","tag":"span","props":{"style":"--shiki-default:#24292E;--shiki-dark:#E1E4E8"},"children":[{"type":"text","value":">\n"}]}]}]}]},{"type":"element","tag":"h2","props":{"id":"使用-ui-库预设"},"children":[{"type":"text","value":"使用 UI 库预设"}]},{"type":"element","tag":"p","props":{},"children":[{"type":"text","value":"对于已内置预设的 UI 库，直接传入 "},{"type":"element","tag":"code","props":{"className":[]},"children":[{"type":"text","value":"preset"}]},{"type":"text","value":" 即可，无需手动查找滚动容器选择器："}]},{"type":"element","tag":"pre","props":{"className":"language-vue shiki shiki-themes github-light github-dark","code":"<template>\n  <!-- Element Plus -->\n  <div v-table-touch-scroll=\"{ preset: 'element-plus' }\">\n    <el-table :data=\"tableData\">\n      <el-table-column prop=\"name\" label=\"Name\" />\n    </el-table>\n  </div>\n\n  <!-- Ant Design Vue -->\n  <div v-table-touch-scroll=\"{ preset: 'ant-design-vue' }\">\n    <a-table :data-source=\"dataSource\" :columns=\"columns\" />\n  </div>\n\n  <!-- VxeTable -->\n  <div v-table-touch-scroll=\"{ preset: 'vxe-table' }\">\n    <vxe-table :data=\"tableData\">\n      <vxe-column field=\"name\" title=\"Name\" />\n    </vxe-table>\n  </div>\n</template>\n","language":"vue","meta":"","style":""},"children":[{"type":"element","tag":"code","props":{"__ignoreMap":""},"children":[{"type":"element","tag":"span","props":{"class":"line","line":1},"children":[{"type":"element","tag":"span","props":{"style":"--shiki-default:#24292E;--shiki-dark:#E1E4E8"},"children":[{"type":"text","value":"<"}]},{"type":"element","tag":"span","props":{"style":"--shiki-default:#22863A;--shiki-dark:#85E89D"},"children":[{"type":"text","value":"template"}]},{"type":"element","tag":"span","props":{"style":"--shiki-default:#24292E;--shiki-dark:#E1E4E8"},"children":[{"type":"text","value":">\n"}]}]},{"type":"element","tag":"span","props":{"class":"line","line":2},"children":[{"type":"element","tag":"span","props":{"style":"--shiki-default:#6A737D;--shiki-dark:#6A737D"},"children":[{"type":"text","value":"  <!-- Element Plus -->\n"}]}]},{"type":"element","tag":"span","props":{"class":"line","line":3},"children":[{"type":"element","tag":"span","props":{"style":"--shiki-default:#24292E;--shiki-dark:#E1E4E8"},"children":[{"type":"text","value":"  <"}]},{"type":"element","tag":"span","props":{"style":"--shiki-default:#22863A;--shiki-dark:#85E89D"},"children":[{"type":"text","value":"div"}]},{"type":"element","tag":"span","props":{"style":"--shiki-default:#6F42C1;--shiki-dark:#B392F0"},"children":[{"type":"text","value":" v-table-touch-scroll"}]},{"type":"element","tag":"span","props":{"style":"--shiki-default:#24292E;--shiki-dark:#E1E4E8"},"children":[{"type":"text","value":"="}]},{"type":"element","tag":"span","props":{"style":"--shiki-default:#032F62;--shiki-dark:#9ECBFF"},"children":[{"type":"text","value":"\"{ preset: 'element-plus' }\""}]},{"type":"element","tag":"span","props":{"style":"--shiki-default:#24292E;--shiki-dark:#E1E4E8"},"children":[{"type":"text","value":">\n"}]}]},{"type":"element","tag":"span","props":{"class":"line","line":4},"children":[{"type":"element","tag":"span","props":{"style":"--shiki-default:#24292E;--shiki-dark:#E1E4E8"},"children":[{"type":"text","value":"    <"}]},{"type":"element","tag":"span","props":{"style":"--shiki-default:#22863A;--shiki-dark:#85E89D"},"children":[{"type":"text","value":"el-table"}]},{"type":"element","tag":"span","props":{"style":"--shiki-default:#6F42C1;--shiki-dark:#B392F0"},"children":[{"type":"text","value":" :data"}]},{"type":"element","tag":"span","props":{"style":"--shiki-default:#24292E;--shiki-dark:#E1E4E8"},"children":[{"type":"text","value":"="}]},{"type":"element","tag":"span","props":{"style":"--shiki-default:#032F62;--shiki-dark:#9ECBFF"},"children":[{"type":"text","value":"\"tableData\""}]},{"type":"element","tag":"span","props":{"style":"--shiki-default:#24292E;--shiki-dark:#E1E4E8"},"children":[{"type":"text","value":">\n"}]}]},{"type":"element","tag":"span","props":{"class":"line","line":5},"children":[{"type":"element","tag":"span","props":{"style":"--shiki-default:#24292E;--shiki-dark:#E1E4E8"},"children":[{"type":"text","value":"      <"}]},{"type":"element","tag":"span","props":{"style":"--shiki-default:#22863A;--shiki-dark:#85E89D"},"children":[{"type":"text","value":"el-table-column"}]},{"type":"element","tag":"span","props":{"style":"--shiki-default:#6F42C1;--shiki-dark:#B392F0"},"children":[{"type":"text","value":" prop"}]},{"type":"element","tag":"span","props":{"style":"--shiki-default:#24292E;--shiki-dark:#E1E4E8"},"children":[{"type":"text","value":"="}]},{"type":"element","tag":"span","props":{"style":"--shiki-default:#032F62;--shiki-dark:#9ECBFF"},"children":[{"type":"text","value":"\"name\""}]},{"type":"element","tag":"span","props":{"style":"--shiki-default:#6F42C1;--shiki-dark:#B392F0"},"children":[{"type":"text","value":" label"}]},{"type":"element","tag":"span","props":{"style":"--shiki-default:#24292E;--shiki-dark:#E1E4E8"},"children":[{"type":"text","value":"="}]},{"type":"element","tag":"span","props":{"style":"--shiki-default:#032F62;--shiki-dark:#9ECBFF"},"children":[{"type":"text","value":"\"Name\""}]},{"type":"element","tag":"span","props":{"style":"--shiki-default:#24292E;--shiki-dark:#E1E4E8"},"children":[{"type":"text","value":" />\n"}]}]},{"type":"element","tag":"span","props":{"class":"line","line":6},"children":[{"type":"element","tag":"span","props":{"style":"--shiki-default:#24292E;--shiki-dark:#E1E4E8"},"children":[{"type":"text","value":"    </"}]},{"type":"element","tag":"span","props":{"style":"--shiki-default:#22863A;--shiki-dark:#85E89D"},"children":[{"type":"text","value":"el-table"}]},{"type":"element","tag":"span","props":{"style":"--shiki-default:#24292E;--shiki-dark:#E1E4E8"},"children":[{"type":"text","value":">\n"}]}]},{"type":"element","tag":"span","props":{"class":"line","line":7},"children":[{"type":"element","tag":"span","props":{"style":"--shiki-default:#24292E;--shiki-dark:#E1E4E8"},"children":[{"type":"text","value":"  </"}]},{"type":"element","tag":"span","props":{"style":"--shiki-default:#22863A;--shiki-dark:#85E89D"},"children":[{"type":"text","value":"div"}]},{"type":"element","tag":"span","props":{"style":"--shiki-default:#24292E;--shiki-dark:#E1E4E8"},"children":[{"type":"text","value":">\n"}]}]},{"type":"element","tag":"span","props":{"class":"line","line":8},"children":[{"type":"element","tag":"span","props":{"emptyLinePlaceholder":true},"children":[{"type":"text","value":"\n"}]}]},{"type":"element","tag":"span","props":{"class":"line","line":9},"children":[{"type":"element","tag":"span","props":{"style":"--shiki-default:#6A737D;--shiki-dark:#6A737D"},"children":[{"type":"text","value":"  <!-- Ant Design Vue -->\n"}]}]},{"type":"element","tag":"span","props":{"class":"line","line":10},"children":[{"type":"element","tag":"span","props":{"style":"--shiki-default:#24292E;--shiki-dark:#E1E4E8"},"children":[{"type":"text","value":"  <"}]},{"type":"element","tag":"span","props":{"style":"--shiki-default:#22863A;--shiki-dark:#85E89D"},"children":[{"type":"text","value":"div"}]},{"type":"element","tag":"span","props":{"style":"--shiki-default:#6F42C1;--shiki-dark:#B392F0"},"children":[{"type":"text","value":" v-table-touch-scroll"}]},{"type":"element","tag":"span","props":{"style":"--shiki-default:#24292E;--shiki-dark:#E1E4E8"},"children":[{"type":"text","value":"="}]},{"type":"element","tag":"span","props":{"style":"--shiki-default:#032F62;--shiki-dark:#9ECBFF"},"children":[{"type":"text","value":"\"{ preset: 'ant-design-vue' }\""}]},{"type":"element","tag":"span","props":{"style":"--shiki-default:#24292E;--shiki-dark:#E1E4E8"},"children":[{"type":"text","value":">\n"}]}]},{"type":"element","tag":"span","props":{"class":"line","line":11},"children":[{"type":"element","tag":"span","props":{"style":"--shiki-default:#24292E;--shiki-dark:#E1E4E8"},"children":[{"type":"text","value":"    <"}]},{"type":"element","tag":"span","props":{"style":"--shiki-default:#22863A;--shiki-dark:#85E89D"},"children":[{"type":"text","value":"a-table"}]},{"type":"element","tag":"span","props":{"style":"--shiki-default:#6F42C1;--shiki-dark:#B392F0"},"children":[{"type":"text","value":" :data-source"}]},{"type":"element","tag":"span","props":{"style":"--shiki-default:#24292E;--shiki-dark:#E1E4E8"},"children":[{"type":"text","value":"="}]},{"type":"element","tag":"span","props":{"style":"--shiki-default:#032F62;--shiki-dark:#9ECBFF"},"children":[{"type":"text","value":"\"dataSource\""}]},{"type":"element","tag":"span","props":{"style":"--shiki-default:#6F42C1;--shiki-dark:#B392F0"},"children":[{"type":"text","value":" :columns"}]},{"type":"element","tag":"span","props":{"style":"--shiki-default:#24292E;--shiki-dark:#E1E4E8"},"children":[{"type":"text","value":"="}]},{"type":"element","tag":"span","props":{"style":"--shiki-default:#032F62;--shiki-dark:#9ECBFF"},"children":[{"type":"text","value":"\"columns\""}]},{"type":"element","tag":"span","props":{"style":"--shiki-default:#24292E;--shiki-dark:#E1E4E8"},"children":[{"type":"text","value":" />\n"}]}]},{"type":"element","tag":"span","props":{"class":"line","line":12},"children":[{"type":"element","tag":"span","props":{"style":"--shiki-default:#24292E;--shiki-dark:#E1E4E8"},"children":[{"type":"text","value":"  </"}]},{"type":"element","tag":"span","props":{"style":"--shiki-default:#22863A;--shiki-dark:#85E89D"},"children":[{"type":"text","value":"div"}]},{"type":"element","tag":"span","props":{"style":"--shiki-default:#24292E;--shiki-dark:#E1E4E8"},"children":[{"type":"text","value":">\n"}]}]},{"type":"element","tag":"span","props":{"class":"line","line":13},"children":[{"type":"element","tag":"span","props":{"emptyLinePlaceholder":true},"children":[{"type":"text","value":"\n"}]}]},{"type":"element","tag":"span","props":{"class":"line","line":14},"children":[{"type":"element","tag":"span","props":{"style":"--shiki-default:#6A737D;--shiki-dark:#6A737D"},"children":[{"type":"text","value":"  <!-- VxeTable -->\n"}]}]},{"type":"element","tag":"span","props":{"class":"line","line":15},"children":[{"type":"element","tag":"span","props":{"style":"--shiki-default:#24292E;--shiki-dark:#E1E4E8"},"children":[{"type":"text","value":"  <"}]},{"type":"element","tag":"span","props":{"style":"--shiki-default:#22863A;--shiki-dark:#85E89D"},"children":[{"type":"text","value":"div"}]},{"type":"element","tag":"span","props":{"style":"--shiki-default:#6F42C1;--shiki-dark:#B392F0"},"children":[{"type":"text","value":" v-table-touch-scroll"}]},{"type":"element","tag":"span","props":{"style":"--shiki-default:#24292E;--shiki-dark:#E1E4E8"},"children":[{"type":"text","value":"="}]},{"type":"element","tag":"span","props":{"style":"--shiki-default:#032F62;--shiki-dark:#9ECBFF"},"children":[{"type":"text","value":"\"{ preset: 'vxe-table' }\""}]},{"type":"element","tag":"span","props":{"style":"--shiki-default:#24292E;--shiki-dark:#E1E4E8"},"children":[{"type":"text","value":">\n"}]}]},{"type":"element","tag":"span","props":{"class":"line","line":16},"children":[{"type":"element","tag":"span","props":{"style":"--shiki-default:#24292E;--shiki-dark:#E1E4E8"},"children":[{"type":"text","value":"    <"}]},{"type":"element","tag":"span","props":{"style":"--shiki-default:#22863A;--shiki-dark:#85E89D"},"children":[{"type":"text","value":"vxe-table"}]},{"type":"element","tag":"span","props":{"style":"--shiki-default:#6F42C1;--shiki-dark:#B392F0"},"children":[{"type":"text","value":" :data"}]},{"type":"element","tag":"span","props":{"style":"--shiki-default:#24292E;--shiki-dark:#E1E4E8"},"children":[{"type":"text","value":"="}]},{"type":"element","tag":"span","props":{"style":"--shiki-default:#032F62;--shiki-dark:#9ECBFF"},"children":[{"type":"text","value":"\"tableData\""}]},{"type":"element","tag":"span","props":{"style":"--shiki-default:#24292E;--shiki-dark:#E1E4E8"},"children":[{"type":"text","value":">\n"}]}]},{"type":"element","tag":"span","props":{"class":"line","line":17},"children":[{"type":"element","tag":"span","props":{"style":"--shiki-default:#24292E;--shiki-dark:#E1E4E8"},"children":[{"type":"text","value":"      <"}]},{"type":"element","tag":"span","props":{"style":"--shiki-default:#22863A;--shiki-dark:#85E89D"},"children":[{"type":"text","value":"vxe-column"}]},{"type":"element","tag":"span","props":{"style":"--shiki-default:#6F42C1;--shiki-dark:#B392F0"},"children":[{"type":"text","value":" field"}]},{"type":"element","tag":"span","props":{"style":"--shiki-default:#24292E;--shiki-dark:#E1E4E8"},"children":[{"type":"text","value":"="}]},{"type":"element","tag":"span","props":{"style":"--shiki-default:#032F62;--shiki-dark:#9ECBFF"},"children":[{"type":"text","value":"\"name\""}]},{"type":"element","tag":"span","props":{"style":"--shiki-default:#6F42C1;--shiki-dark:#B392F0"},"children":[{"type":"text","value":" title"}]},{"type":"element","tag":"span","props":{"style":"--shiki-default:#24292E;--shiki-dark:#E1E4E8"},"children":[{"type":"text","value":"="}]},{"type":"element","tag":"span","props":{"style":"--shiki-default:#032F62;--shiki-dark:#9ECBFF"},"children":[{"type":"text","value":"\"Name\""}]},{"type":"element","tag":"span","props":{"style":"--shiki-default:#24292E;--shiki-dark:#E1E4E8"},"children":[{"type":"text","value":" />\n"}]}]},{"type":"element","tag":"span","props":{"class":"line","line":18},"children":[{"type":"element","tag":"span","props":{"style":"--shiki-default:#24292E;--shiki-dark:#E1E4E8"},"children":[{"type":"text","value":"    </"}]},{"type":"element","tag":"span","props":{"style":"--shiki-default:#22863A;--shiki-dark:#85E89D"},"children":[{"type":"text","value":"vxe-table"}]},{"type":"element","tag":"span","props":{"style":"--shiki-default:#24292E;--shiki-dark:#E1E4E8"},"children":[{"type":"text","value":">\n"}]}]},{"type":"element","tag":"span","props":{"class":"line","line":19},"children":[{"type":"element","tag":"span","props":{"style":"--shiki-default:#24292E;--shiki-dark:#E1E4E8"},"children":[{"type":"text","value":"  </"}]},{"type":"element","tag":"span","props":{"style":"--shiki-default:#22863A;--shiki-dark:#85E89D"},"children":[{"type":"text","value":"div"}]},{"type":"element","tag":"span","props":{"style":"--shiki-default:#24292E;--shiki-dark:#E1E4E8"},"children":[{"type":"text","value":">\n"}]}]},{"type":"element","tag":"span","props":{"class":"line","line":20},"children":[{"type":"element","tag":"span","props":{"style":"--shiki-default:#24292E;--shiki-dark:#E1E4E8"},"children":[{"type":"text","value":"</"}]},{"type":"element","tag":"span","props":{"style":"--shiki-default:#22863A;--shiki-dark:#85E89D"},"children":[{"type":"text","value":"template"}]},{"type":"element","tag":"span","props":{"style":"--shiki-default:#24292E;--shiki-dark:#E1E4E8"},"children":[{"type":"text","value":">\n"}]}]}]}]},{"type":"element","tag":"callout","props":{"icon":"lucide:info"},"children":[{"type":"element","tag":"p","props":{},"children":[{"type":"text","value":"支持的预设列表和对应选择器请查看 "},{"type":"element","tag":"a","props":{"href":"/zh/api/parameters#tablepreset"},"children":[{"type":"text","value":"API — TablePreset"}]},{"type":"text","value":"。"}]}]},{"type":"element","tag":"h2","props":{"id":"使用自定义选择器"},"children":[{"type":"text","value":"使用自定义选择器"}]},{"type":"element","tag":"p","props":{},"children":[{"type":"text","value":"对于没有内置预设的 UI 库，通过 "},{"type":"element","tag":"code","props":{"className":[]},"children":[{"type":"text","value":"selector"}]},{"type":"text","value":" 指定表格内部的滚动容器："}]},{"type":"element","tag":"pre","props":{"className":"language-vue shiki shiki-themes github-light github-dark","code":"<template>\n  <div v-table-touch-scroll=\"{ selector: '.my-scroll-container' }\">\n    <MyTable />\n  </div>\n</template>\n","language":"vue","meta":"","style":""},"children":[{"type":"element","tag":"code","props":{"__ignoreMap":""},"children":[{"type":"element","tag":"span","props":{"class":"line","line":1},"children":[{"type":"element","tag":"span","props":{"style":"--shiki-default:#24292E;--shiki-dark:#E1E4E8"},"children":[{"type":"text","value":"<"}]},{"type":"element","tag":"span","props":{"style":"--shiki-default:#22863A;--shiki-dark:#85E89D"},"children":[{"type":"text","value":"template"}]},{"type":"element","tag":"span","props":{"style":"--shiki-default:#24292E;--shiki-dark:#E1E4E8"},"children":[{"type":"text","value":">\n"}]}]},{"type":"element","tag":"span","props":{"class":"line","line":2},"children":[{"type":"element","tag":"span","props":{"style":"--shiki-default:#24292E;--shiki-dark:#E1E4E8"},"children":[{"type":"text","value":"  <"}]},{"type":"element","tag":"span","props":{"style":"--shiki-default:#22863A;--shiki-dark:#85E89D"},"children":[{"type":"text","value":"div"}]},{"type":"element","tag":"span","props":{"style":"--shiki-default:#6F42C1;--shiki-dark:#B392F0"},"children":[{"type":"text","value":" v-table-touch-scroll"}]},{"type":"element","tag":"span","props":{"style":"--shiki-default:#24292E;--shiki-dark:#E1E4E8"},"children":[{"type":"text","value":"="}]},{"type":"element","tag":"span","props":{"style":"--shiki-default:#032F62;--shiki-dark:#9ECBFF"},"children":[{"type":"text","value":"\"{ selector: '.my-scroll-container' }\""}]},{"type":"element","tag":"span","props":{"style":"--shiki-default:#24292E;--shiki-dark:#E1E4E8"},"children":[{"type":"text","value":">\n"}]}]},{"type":"element","tag":"span","props":{"class":"line","line":3},"children":[{"type":"element","tag":"span","props":{"style":"--shiki-default:#24292E;--shiki-dark:#E1E4E8"},"children":[{"type":"text","value":"    <"}]},{"type":"element","tag":"span","props":{"style":"--shiki-default:#22863A;--shiki-dark:#85E89D"},"children":[{"type":"text","value":"MyTable"}]},{"type":"element","tag":"span","props":{"style":"--shiki-default:#24292E;--shiki-dark:#E1E4E8"},"children":[{"type":"text","value":" />\n"}]}]},{"type":"element","tag":"span","props":{"class":"line","line":4},"children":[{"type":"element","tag":"span","props":{"style":"--shiki-default:#24292E;--shiki-dark:#E1E4E8"},"children":[{"type":"text","value":"  </"}]},{"type":"element","tag":"span","props":{"style":"--shiki-default:#22863A;--shiki-dark:#85E89D"},"children":[{"type":"text","value":"div"}]},{"type":"element","tag":"span","props":{"style":"--shiki-default:#24292E;--shiki-dark:#E1E4E8"},"children":[{"type":"text","value":">\n"}]}]},{"type":"element","tag":"span","props":{"class":"line","line":5},"children":[{"type":"element","tag":"span","props":{"style":"--shiki-default:#24292E;--shiki-dark:#E1E4E8"},"children":[{"type":"text","value":"</"}]},{"type":"element","tag":"span","props":{"style":"--shiki-default:#22863A;--shiki-dark:#85E89D"},"children":[{"type":"text","value":"template"}]},{"type":"element","tag":"span","props":{"style":"--shiki-default:#24292E;--shiki-dark:#E1E4E8"},"children":[{"type":"text","value":">\n"}]}]}]}]},{"type":"element","tag":"callout","props":{"icon":"lucide:triangle-alert","color":"amber"},"children":[{"type":"element","tag":"p","props":{},"children":[{"type":"element","tag":"code","props":{"className":[]},"children":[{"type":"text","value":"selector"}]},{"type":"text","value":" 的优先级高于 "},{"type":"element","tag":"code","props":{"className":[]},"children":[{"type":"text","value":"preset"}]},{"type":"text","value":"。如果两者同时提供，将使用 "},{"type":"element","tag":"code","props":{"className":[]},"children":[{"type":"text","value":"selector"}]},{"type":"text","value":" 指定的元素。如果都未提供，则默认使用绑定指令的元素本身。"}]}]},{"type":"element","tag":"h2","props":{"id":"自定义物理参数"},"children":[{"type":"text","value":"自定义物理参数"}]},{"type":"element","tag":"p","props":{},"children":[{"type":"text","value":"根据使用场景调整摩擦力和拖拽阈值："}]},{"type":"element","tag":"pre","props":{"className":"language-vue shiki shiki-themes github-light github-dark","code":"<template>\n  <!-- 更丝滑：高摩擦力（衰减慢），低阈值 -->\n  <div v-table-touch-scroll=\"{ preset: 'element-plus', friction: 0.98, dragThreshold: 3 }\">\n    <el-table :data=\"tableData\" />\n  </div>\n\n  <!-- 更精确：低摩擦力（衰减快），高阈值 -->\n  <div v-table-touch-scroll=\"{ preset: 'element-plus', friction: 0.85, dragThreshold: 10 }\">\n    <el-table :data=\"tableData\" />\n  </div>\n</template>\n","language":"vue","meta":"","style":""},"children":[{"type":"element","tag":"code","props":{"__ignoreMap":""},"children":[{"type":"element","tag":"span","props":{"class":"line","line":1},"children":[{"type":"element","tag":"span","props":{"style":"--shiki-default:#24292E;--shiki-dark:#E1E4E8"},"children":[{"type":"text","value":"<"}]},{"type":"element","tag":"span","props":{"style":"--shiki-default:#22863A;--shiki-dark:#85E89D"},"children":[{"type":"text","value":"template"}]},{"type":"element","tag":"span","props":{"style":"--shiki-default:#24292E;--shiki-dark:#E1E4E8"},"children":[{"type":"text","value":">\n"}]}]},{"type":"element","tag":"span","props":{"class":"line","line":2},"children":[{"type":"element","tag":"span","props":{"style":"--shiki-default:#6A737D;--shiki-dark:#6A737D"},"children":[{"type":"text","value":"  <!-- 更丝滑：高摩擦力（衰减慢），低阈值 -->\n"}]}]},{"type":"element","tag":"span","props":{"class":"line","line":3},"children":[{"type":"element","tag":"span","props":{"style":"--shiki-default:#24292E;--shiki-dark:#E1E4E8"},"children":[{"type":"text","value":"  <"}]},{"type":"element","tag":"span","props":{"style":"--shiki-default:#22863A;--shiki-dark:#85E89D"},"children":[{"type":"text","value":"div"}]},{"type":"element","tag":"span","props":{"style":"--shiki-default:#6F42C1;--shiki-dark:#B392F0"},"children":[{"type":"text","value":" v-table-touch-scroll"}]},{"type":"element","tag":"span","props":{"style":"--shiki-default:#24292E;--shiki-dark:#E1E4E8"},"children":[{"type":"text","value":"="}]},{"type":"element","tag":"span","props":{"style":"--shiki-default:#032F62;--shiki-dark:#9ECBFF"},"children":[{"type":"text","value":"\"{ preset: 'element-plus', friction: 0.98, dragThreshold: 3 }\""}]},{"type":"element","tag":"span","props":{"style":"--shiki-default:#24292E;--shiki-dark:#E1E4E8"},"children":[{"type":"text","value":">\n"}]}]},{"type":"element","tag":"span","props":{"class":"line","line":4},"children":[{"type":"element","tag":"span","props":{"style":"--shiki-default:#24292E;--shiki-dark:#E1E4E8"},"children":[{"type":"text","value":"    <"}]},{"type":"element","tag":"span","props":{"style":"--shiki-default:#22863A;--shiki-dark:#85E89D"},"children":[{"type":"text","value":"el-table"}]},{"type":"element","tag":"span","props":{"style":"--shiki-default:#6F42C1;--shiki-dark:#B392F0"},"children":[{"type":"text","value":" :data"}]},{"type":"element","tag":"span","props":{"style":"--shiki-default:#24292E;--shiki-dark:#E1E4E8"},"children":[{"type":"text","value":"="}]},{"type":"element","tag":"span","props":{"style":"--shiki-default:#032F62;--shiki-dark:#9ECBFF"},"children":[{"type":"text","value":"\"tableData\""}]},{"type":"element","tag":"span","props":{"style":"--shiki-default:#24292E;--shiki-dark:#E1E4E8"},"children":[{"type":"text","value":" />\n"}]}]},{"type":"element","tag":"span","props":{"class":"line","line":5},"children":[{"type":"element","tag":"span","props":{"style":"--shiki-default:#24292E;--shiki-dark:#E1E4E8"},"children":[{"type":"text","value":"  </"}]},{"type":"element","tag":"span","props":{"style":"--shiki-default:#22863A;--shiki-dark:#85E89D"},"children":[{"type":"text","value":"div"}]},{"type":"element","tag":"span","props":{"style":"--shiki-default:#24292E;--shiki-dark:#E1E4E8"},"children":[{"type":"text","value":">\n"}]}]},{"type":"element","tag":"span","props":{"class":"line","line":6},"children":[{"type":"element","tag":"span","props":{"emptyLinePlaceholder":true},"children":[{"type":"text","value":"\n"}]}]},{"type":"element","tag":"span","props":{"class":"line","line":7},"children":[{"type":"element","tag":"span","props":{"style":"--shiki-default:#6A737D;--shiki-dark:#6A737D"},"children":[{"type":"text","value":"  <!-- 更精确：低摩擦力（衰减快），高阈值 -->\n"}]}]},{"type":"element","tag":"span","props":{"class":"line","line":8},"children":[{"type":"element","tag":"span","props":{"style":"--shiki-default:#24292E;--shiki-dark:#E1E4E8"},"children":[{"type":"text","value":"  <"}]},{"type":"element","tag":"span","props":{"style":"--shiki-default:#22863A;--shiki-dark:#85E89D"},"children":[{"type":"text","value":"div"}]},{"type":"element","tag":"span","props":{"style":"--shiki-default:#6F42C1;--shiki-dark:#B392F0"},"children":[{"type":"text","value":" v-table-touch-scroll"}]},{"type":"element","tag":"span","props":{"style":"--shiki-default:#24292E;--shiki-dark:#E1E4E8"},"children":[{"type":"text","value":"="}]},{"type":"element","tag":"span","props":{"style":"--shiki-default:#032F62;--shiki-dark:#9ECBFF"},"children":[{"type":"text","value":"\"{ preset: 'element-plus', friction: 0.85, dragThreshold: 10 }\""}]},{"type":"element","tag":"span","props":{"style":"--shiki-default:#24292E;--shiki-dark:#E1E4E8"},"children":[{"type":"text","value":">\n"}]}]},{"type":"element","tag":"span","props":{"class":"line","line":9},"children":[{"type":"element","tag":"span","props":{"style":"--shiki-default:#24292E;--shiki-dark:#E1E4E8"},"children":[{"type":"text","value":"    <"}]},{"type":"element","tag":"span","props":{"style":"--shiki-default:#22863A;--shiki-dark:#85E89D"},"children":[{"type":"text","value":"el-table"}]},{"type":"element","tag":"span","props":{"style":"--shiki-default:#6F42C1;--shiki-dark:#B392F0"},"children":[{"type":"text","value":" :data"}]},{"type":"element","tag":"span","props":{"style":"--shiki-default:#24292E;--shiki-dark:#E1E4E8"},"children":[{"type":"text","value":"="}]},{"type":"element","tag":"span","props":{"style":"--shiki-default:#032F62;--shiki-dark:#9ECBFF"},"children":[{"type":"text","value":"\"tableData\""}]},{"type":"element","tag":"span","props":{"style":"--shiki-default:#24292E;--shiki-dark:#E1E4E8"},"children":[{"type":"text","value":" />\n"}]}]},{"type":"element","tag":"span","props":{"class":"line","line":10},"children":[{"type":"element","tag":"span","props":{"style":"--shiki-default:#24292E;--shiki-dark:#E1E4E8"},"children":[{"type":"text","value":"  </"}]},{"type":"element","tag":"span","props":{"style":"--shiki-default:#22863A;--shiki-dark:#85E89D"},"children":[{"type":"text","value":"div"}]},{"type":"element","tag":"span","props":{"style":"--shiki-default:#24292E;--shiki-dark:#E1E4E8"},"children":[{"type":"text","value":">\n"}]}]},{"type":"element","tag":"span","props":{"class":"line","line":11},"children":[{"type":"element","tag":"span","props":{"style":"--shiki-default:#24292E;--shiki-dark:#E1E4E8"},"children":[{"type":"text","value":"</"}]},{"type":"element","tag":"span","props":{"style":"--shiki-default:#22863A;--shiki-dark:#85E89D"},"children":[{"type":"text","value":"template"}]},{"type":"element","tag":"span","props":{"style":"--shiki-default:#24292E;--shiki-dark:#E1E4E8"},"children":[{"type":"text","value":">\n"}]}]}]}]},{"type":"element","tag":"h2","props":{"id":"动态控制"},"children":[{"type":"text","value":"动态控制"}]},{"type":"element","tag":"p","props":{},"children":[{"type":"text","value":"传入 "},{"type":"element","tag":"code","props":{"className":[]},"children":[{"type":"text","value":"false"}]},{"type":"text","value":" 可完全禁用指令——所有事件监听和样式劫持都会被彻底清理："}]},{"type":"element","tag":"pre","props":{"className":"language-vue shiki shiki-themes github-light github-dark","code":"<template>\n  <div v-table-touch-scroll=\"enableTouchScroll ? { preset: 'element-plus' } : false\">\n    <el-table :data=\"tableData\" />\n  </div>\n</template>\n\n<script setup lang=\"ts\">\nimport { ref } from 'vue'\n\nconst enableTouchScroll = ref(true)\n</script>\n","language":"vue","meta":"","style":""},"children":[{"type":"element","tag":"code","props":{"__ignoreMap":""},"children":[{"type":"element","tag":"span","props":{"class":"line","line":1},"children":[{"type":"element","tag":"span","props":{"style":"--shiki-default:#24292E;--shiki-dark:#E1E4E8"},"children":[{"type":"text","value":"<"}]},{"type":"element","tag":"span","props":{"style":"--shiki-default:#22863A;--shiki-dark:#85E89D"},"children":[{"type":"text","value":"template"}]},{"type":"element","tag":"span","props":{"style":"--shiki-default:#24292E;--shiki-dark:#E1E4E8"},"children":[{"type":"text","value":">\n"}]}]},{"type":"element","tag":"span","props":{"class":"line","line":2},"children":[{"type":"element","tag":"span","props":{"style":"--shiki-default:#24292E;--shiki-dark:#E1E4E8"},"children":[{"type":"text","value":"  <"}]},{"type":"element","tag":"span","props":{"style":"--shiki-default:#22863A;--shiki-dark:#85E89D"},"children":[{"type":"text","value":"div"}]},{"type":"element","tag":"span","props":{"style":"--shiki-default:#6F42C1;--shiki-dark:#B392F0"},"children":[{"type":"text","value":" v-table-touch-scroll"}]},{"type":"element","tag":"span","props":{"style":"--shiki-default:#24292E;--shiki-dark:#E1E4E8"},"children":[{"type":"text","value":"="}]},{"type":"element","tag":"span","props":{"style":"--shiki-default:#032F62;--shiki-dark:#9ECBFF"},"children":[{"type":"text","value":"\"enableTouchScroll ? { preset: 'element-plus' } : false\""}]},{"type":"element","tag":"span","props":{"style":"--shiki-default:#24292E;--shiki-dark:#E1E4E8"},"children":[{"type":"text","value":">\n"}]}]},{"type":"element","tag":"span","props":{"class":"line","line":3},"children":[{"type":"element","tag":"span","props":{"style":"--shiki-default:#24292E;--shiki-dark:#E1E4E8"},"children":[{"type":"text","value":"    <"}]},{"type":"element","tag":"span","props":{"style":"--shiki-default:#22863A;--shiki-dark:#85E89D"},"children":[{"type":"text","value":"el-table"}]},{"type":"element","tag":"span","props":{"style":"--shiki-default:#6F42C1;--shiki-dark:#B392F0"},"children":[{"type":"text","value":" :data"}]},{"type":"element","tag":"span","props":{"style":"--shiki-default:#24292E;--shiki-dark:#E1E4E8"},"children":[{"type":"text","value":"="}]},{"type":"element","tag":"span","props":{"style":"--shiki-default:#032F62;--shiki-dark:#9ECBFF"},"children":[{"type":"text","value":"\"tableData\""}]},{"type":"element","tag":"span","props":{"style":"--shiki-default:#24292E;--shiki-dark:#E1E4E8"},"children":[{"type":"text","value":" />\n"}]}]},{"type":"element","tag":"span","props":{"class":"line","line":4},"children":[{"type":"element","tag":"span","props":{"style":"--shiki-default:#24292E;--shiki-dark:#E1E4E8"},"children":[{"type":"text","value":"  </"}]},{"type":"element","tag":"span","props":{"style":"--shiki-default:#22863A;--shiki-dark:#85E89D"},"children":[{"type":"text","value":"div"}]},{"type":"element","tag":"span","props":{"style":"--shiki-default:#24292E;--shiki-dark:#E1E4E8"},"children":[{"type":"text","value":">\n"}]}]},{"type":"element","tag":"span","props":{"class":"line","line":5},"children":[{"type":"element","tag":"span","props":{"style":"--shiki-default:#24292E;--shiki-dark:#E1E4E8"},"children":[{"type":"text","value":"</"}]},{"type":"element","tag":"span","props":{"style":"--shiki-default:#22863A;--shiki-dark:#85E89D"},"children":[{"type":"text","value":"template"}]},{"type":"element","tag":"span","props":{"style":"--shiki-default:#24292E;--shiki-dark:#E1E4E8"},"children":[{"type":"text","value":">\n"}]}]},{"type":"element","tag":"span","props":{"class":"line","line":6},"children":[{"type":"element","tag":"span","props":{"emptyLinePlaceholder":true},"children":[{"type":"text","value":"\n"}]}]},{"type":"element","tag":"span","props":{"class":"line","line":7},"children":[{"type":"element","tag":"span","props":{"style":"--shiki-default:#24292E;--shiki-dark:#E1E4E8"},"children":[{"type":"text","value":"<"}]},{"type":"element","tag":"span","props":{"style":"--shiki-default:#22863A;--shiki-dark:#85E89D"},"children":[{"type":"text","value":"script"}]},{"type":"element","tag":"span","props":{"style":"--shiki-default:#6F42C1;--shiki-dark:#B392F0"},"children":[{"type":"text","value":" setup"}]},{"type":"element","tag":"span","props":{"style":"--shiki-default:#6F42C1;--shiki-dark:#B392F0"},"children":[{"type":"text","value":" lang"}]},{"type":"element","tag":"span","props":{"style":"--shiki-default:#24292E;--shiki-dark:#E1E4E8"},"children":[{"type":"text","value":"="}]},{"type":"element","tag":"span","props":{"style":"--shiki-default:#032F62;--shiki-dark:#9ECBFF"},"children":[{"type":"text","value":"\"ts\""}]},{"type":"element","tag":"span","props":{"style":"--shiki-default:#24292E;--shiki-dark:#E1E4E8"},"children":[{"type":"text","value":">\n"}]}]},{"type":"element","tag":"span","props":{"class":"line","line":8},"children":[{"type":"element","tag":"span","props":{"style":"--shiki-default:#D73A49;--shiki-dark:#F97583"},"children":[{"type":"text","value":"import"}]},{"type":"element","tag":"span","props":{"style":"--shiki-default:#24292E;--shiki-dark:#E1E4E8"},"children":[{"type":"text","value":" { ref } "}]},{"type":"element","tag":"span","props":{"style":"--shiki-default:#D73A49;--shiki-dark:#F97583"},"children":[{"type":"text","value":"from"}]},{"type":"element","tag":"span","props":{"style":"--shiki-default:#032F62;--shiki-dark:#9ECBFF"},"children":[{"type":"text","value":" 'vue'\n"}]}]},{"type":"element","tag":"span","props":{"class":"line","line":9},"children":[{"type":"element","tag":"span","props":{"emptyLinePlaceholder":true},"children":[{"type":"text","value":"\n"}]}]},{"type":"element","tag":"span","props":{"class":"line","line":10},"children":[{"type":"element","tag":"span","props":{"style":"--shiki-default:#D73A49;--shiki-dark:#F97583"},"children":[{"type":"text","value":"const"}]},{"type":"element","tag":"span","props":{"style":"--shiki-default:#005CC5;--shiki-dark:#79B8FF"},"children":[{"type":"text","value":" enableTouchScroll"}]},{"type":"element","tag":"span","props":{"style":"--shiki-default:#D73A49;--shiki-dark:#F97583"},"children":[{"type":"text","value":" ="}]},{"type":"element","tag":"span","props":{"style":"--shiki-default:#6F42C1;--shiki-dark:#B392F0"},"children":[{"type":"text","value":" ref"}]},{"type":"element","tag":"span","props":{"style":"--shiki-default:#24292E;--shiki-dark:#E1E4E8"},"children":[{"type":"text","value":"("}]},{"type":"element","tag":"span","props":{"style":"--shiki-default:#005CC5;--shiki-dark:#79B8FF"},"children":[{"type":"text","value":"true"}]},{"type":"element","tag":"span","props":{"style":"--shiki-default:#24292E;--shiki-dark:#E1E4E8"},"children":[{"type":"text","value":")\n"}]}]},{"type":"element","tag":"span","props":{"class":"line","line":11},"children":[{"type":"element","tag":"span","props":{"style":"--shiki-default:#24292E;--shiki-dark:#E1E4E8"},"children":[{"type":"text","value":"</"}]},{"type":"element","tag":"span","props":{"style":"--shiki-default:#22863A;--shiki-dark:#85E89D"},"children":[{"type":"text","value":"script"}]},{"type":"element","tag":"span","props":{"style":"--shiki-default:#24292E;--shiki-dark:#E1E4E8"},"children":[{"type":"text","value":">\n"}]}]}]}]},{"type":"element","tag":"p","props":{},"children":[{"type":"text","value":"也可以通过 "},{"type":"element","tag":"code","props":{"className":[]},"children":[{"type":"text","value":"enabled"}]},{"type":"text","value":" 属性控制，效果完全一致："}]},{"type":"element","tag":"pre","props":{"className":"language-vue shiki shiki-themes github-light github-dark","code":"<template>\n  <div v-table-touch-scroll=\"{ enabled: enableTouchScroll, preset: 'element-plus' }\">\n    <el-table :data=\"tableData\" />\n  </div>\n</template>\n","language":"vue","meta":"","style":""},"children":[{"type":"element","tag":"code","props":{"__ignoreMap":""},"children":[{"type":"element","tag":"span","props":{"class":"line","line":1},"children":[{"type":"element","tag":"span","props":{"style":"--shiki-default:#24292E;--shiki-dark:#E1E4E8"},"children":[{"type":"text","value":"<"}]},{"type":"element","tag":"span","props":{"style":"--shiki-default:#22863A;--shiki-dark:#85E89D"},"children":[{"type":"text","value":"template"}]},{"type":"element","tag":"span","props":{"style":"--shiki-default:#24292E;--shiki-dark:#E1E4E8"},"children":[{"type":"text","value":">\n"}]}]},{"type":"element","tag":"span","props":{"class":"line","line":2},"children":[{"type":"element","tag":"span","props":{"style":"--shiki-default:#24292E;--shiki-dark:#E1E4E8"},"children":[{"type":"text","value":"  <"}]},{"type":"element","tag":"span","props":{"style":"--shiki-default:#22863A;--shiki-dark:#85E89D"},"children":[{"type":"text","value":"div"}]},{"type":"element","tag":"span","props":{"style":"--shiki-default:#6F42C1;--shiki-dark:#B392F0"},"children":[{"type":"text","value":" v-table-touch-scroll"}]},{"type":"element","tag":"span","props":{"style":"--shiki-default:#24292E;--shiki-dark:#E1E4E8"},"children":[{"type":"text","value":"="}]},{"type":"element","tag":"span","props":{"style":"--shiki-default:#032F62;--shiki-dark:#9ECBFF"},"children":[{"type":"text","value":"\"{ enabled: enableTouchScroll, preset: 'element-plus' }\""}]},{"type":"element","tag":"span","props":{"style":"--shiki-default:#24292E;--shiki-dark:#E1E4E8"},"children":[{"type":"text","value":">\n"}]}]},{"type":"element","tag":"span","props":{"class":"line","line":3},"children":[{"type":"element","tag":"span","props":{"style":"--shiki-default:#24292E;--shiki-dark:#E1E4E8"},"children":[{"type":"text","value":"    <"}]},{"type":"element","tag":"span","props":{"style":"--shiki-default:#22863A;--shiki-dark:#85E89D"},"children":[{"type":"text","value":"el-table"}]},{"type":"element","tag":"span","props":{"style":"--shiki-default:#6F42C1;--shiki-dark:#B392F0"},"children":[{"type":"text","value":" :data"}]},{"type":"element","tag":"span","props":{"style":"--shiki-default:#24292E;--shiki-dark:#E1E4E8"},"children":[{"type":"text","value":"="}]},{"type":"element","tag":"span","props":{"style":"--shiki-default:#032F62;--shiki-dark:#9ECBFF"},"children":[{"type":"text","value":"\"tableData\""}]},{"type":"element","tag":"span","props":{"style":"--shiki-default:#24292E;--shiki-dark:#E1E4E8"},"children":[{"type":"text","value":" />\n"}]}]},{"type":"element","tag":"span","props":{"class":"line","line":4},"children":[{"type":"element","tag":"span","props":{"style":"--shiki-default:#24292E;--shiki-dark:#E1E4E8"},"children":[{"type":"text","value":"  </"}]},{"type":"element","tag":"span","props":{"style":"--shiki-default:#22863A;--shiki-dark:#85E89D"},"children":[{"type":"text","value":"div"}]},{"type":"element","tag":"span","props":{"style":"--shiki-default:#24292E;--shiki-dark:#E1E4E8"},"children":[{"type":"text","value":">\n"}]}]},{"type":"element","tag":"span","props":{"class":"line","line":5},"children":[{"type":"element","tag":"span","props":{"style":"--shiki-default:#24292E;--shiki-dark:#E1E4E8"},"children":[{"type":"text","value":"</"}]},{"type":"element","tag":"span","props":{"style":"--shiki-default:#22863A;--shiki-dark:#85E89D"},"children":[{"type":"text","value":"template"}]},{"type":"element","tag":"span","props":{"style":"--shiki-default:#24292E;--shiki-dark:#E1E4E8"},"children":[{"type":"text","value":">\n"}]}]}]}]},{"type":"element","tag":"callout","props":{"icon":"lucide:info"},"children":[{"type":"element","tag":"p","props":{},"children":[{"type":"element","tag":"code","props":{"className":[]},"children":[{"type":"text","value":"enabled: false"}]},{"type":"text","value":" 与传 "},{"type":"element","tag":"code","props":{"className":[]},"children":[{"type":"text","value":"false"}]},{"type":"text","value":" 等价——两者都会完全销毁指令实例（移除所有事件监听并还原原始样式）。你"},{"type":"element","tag":"strong","props":{},"children":[{"type":"text","value":"不需要"}]},{"type":"text","value":"用它来做设备判断，指令的 "},{"type":"element","tag":"code","props":{"className":[]},"children":[{"type":"text","value":"mode: 'auto'"}]},{"type":"text","value":" 已经自动处理了设备检测。"}]}]},{"type":"element","tag":"h2","props":{"id":"设备检测模式"},"children":[{"type":"text","value":"设备检测模式"}]},{"type":"element","tag":"p","props":{},"children":[{"type":"text","value":"默认情况下，指令使用 "},{"type":"element","tag":"code","props":{"className":[]},"children":[{"type":"text","value":"mode: 'auto'"}]},{"type":"text","value":" 自动检测设备类型并采用最优策略："}]},{"type":"element","tag":"ul","props":{},"children":[{"type":"element","tag":"li","props":{},"children":[{"type":"element","tag":"strong","props":{},"children":[{"type":"text","value":"纯 PC"}]},{"type":"text","value":"：休眠状态 — 不绑定任何事件，零开销"}]},{"type":"element","tag":"li","props":{},"children":[{"type":"element","tag":"strong","props":{},"children":[{"type":"text","value":"纯移动端（手机/平板）"}]},{"type":"text","value":"：立即激活完整触摸处理"}]},{"type":"element","tag":"li","props":{},"children":[{"type":"element","tag":"strong","props":{},"children":[{"type":"text","value":"混合设备（Surface / 触屏笔记本）"}]},{"type":"text","value":"：懒接管 — 仅在确认真实触摸拖拽后才激活，避免对鼠标/触控板用户造成干扰"}]}]},{"type":"element","tag":"p","props":{},"children":[{"type":"text","value":"使用 "},{"type":"element","tag":"code","props":{"className":[]},"children":[{"type":"text","value":"mode: 'always'"}]},{"type":"text","value":" 可强制启用触摸处理，忽略设备类型。适用于调试或明确知道目标环境的场景："}]},{"type":"element","tag":"pre","props":{"className":"language-vue shiki shiki-themes github-light github-dark","code":"<template>\n  <div v-table-touch-scroll=\"{ preset: 'element-plus', mode: 'always' }\">\n    <el-table :data=\"tableData\" />\n  </div>\n</template>\n","language":"vue","meta":"","style":""},"children":[{"type":"element","tag":"code","props":{"__ignoreMap":""},"children":[{"type":"element","tag":"span","props":{"class":"line","line":1},"children":[{"type":"element","tag":"span","props":{"style":"--shiki-default:#24292E;--shiki-dark:#E1E4E8"},"children":[{"type":"text","value":"<"}]},{"type":"element","tag":"span","props":{"style":"--shiki-default:#22863A;--shiki-dark:#85E89D"},"children":[{"type":"text","value":"template"}]},{"type":"element","tag":"span","props":{"style":"--shiki-default:#24292E;--shiki-dark:#E1E4E8"},"children":[{"type":"text","value":">\n"}]}]},{"type":"element","tag":"span","props":{"class":"line","line":2},"children":[{"type":"element","tag":"span","props":{"style":"--shiki-default:#24292E;--shiki-dark:#E1E4E8"},"children":[{"type":"text","value":"  <"}]},{"type":"element","tag":"span","props":{"style":"--shiki-default:#22863A;--shiki-dark:#85E89D"},"children":[{"type":"text","value":"div"}]},{"type":"element","tag":"span","props":{"style":"--shiki-default:#6F42C1;--shiki-dark:#B392F0"},"children":[{"type":"text","value":" v-table-touch-scroll"}]},{"type":"element","tag":"span","props":{"style":"--shiki-default:#24292E;--shiki-dark:#E1E4E8"},"children":[{"type":"text","value":"="}]},{"type":"element","tag":"span","props":{"style":"--shiki-default:#032F62;--shiki-dark:#9ECBFF"},"children":[{"type":"text","value":"\"{ preset: 'element-plus', mode: 'always' }\""}]},{"type":"element","tag":"span","props":{"style":"--shiki-default:#24292E;--shiki-dark:#E1E4E8"},"children":[{"type":"text","value":">\n"}]}]},{"type":"element","tag":"span","props":{"class":"line","line":3},"children":[{"type":"element","tag":"span","props":{"style":"--shiki-default:#24292E;--shiki-dark:#E1E4E8"},"children":[{"type":"text","value":"    <"}]},{"type":"element","tag":"span","props":{"style":"--shiki-default:#22863A;--shiki-dark:#85E89D"},"children":[{"type":"text","value":"el-table"}]},{"type":"element","tag":"span","props":{"style":"--shiki-default:#6F42C1;--shiki-dark:#B392F0"},"children":[{"type":"text","value":" :data"}]},{"type":"element","tag":"span","props":{"style":"--shiki-default:#24292E;--shiki-dark:#E1E4E8"},"children":[{"type":"text","value":"="}]},{"type":"element","tag":"span","props":{"style":"--shiki-default:#032F62;--shiki-dark:#9ECBFF"},"children":[{"type":"text","value":"\"tableData\""}]},{"type":"element","tag":"span","props":{"style":"--shiki-default:#24292E;--shiki-dark:#E1E4E8"},"children":[{"type":"text","value":" />\n"}]}]},{"type":"element","tag":"span","props":{"class":"line","line":4},"children":[{"type":"element","tag":"span","props":{"style":"--shiki-default:#24292E;--shiki-dark:#E1E4E8"},"children":[{"type":"text","value":"  </"}]},{"type":"element","tag":"span","props":{"style":"--shiki-default:#22863A;--shiki-dark:#85E89D"},"children":[{"type":"text","value":"div"}]},{"type":"element","tag":"span","props":{"style":"--shiki-default:#24292E;--shiki-dark:#E1E4E8"},"children":[{"type":"text","value":">\n"}]}]},{"type":"element","tag":"span","props":{"class":"line","line":5},"children":[{"type":"element","tag":"span","props":{"style":"--shiki-default:#24292E;--shiki-dark:#E1E4E8"},"children":[{"type":"text","value":"</"}]},{"type":"element","tag":"span","props":{"style":"--shiki-default:#22863A;--shiki-dark:#85E89D"},"children":[{"type":"text","value":"template"}]},{"type":"element","tag":"span","props":{"style":"--shiki-default:#24292E;--shiki-dark:#E1E4E8"},"children":[{"type":"text","value":">\n"}]}]}]}]},{"type":"element","tag":"callout","props":{"icon":"lucide:info"},"children":[{"type":"element","tag":"p","props":{},"children":[{"type":"text","value":"大多数场景下，推荐使用 "},{"type":"element","tag":"code","props":{"className":[]},"children":[{"type":"text","value":"mode: 'auto'"}]},{"type":"text","value":"（默认值）。仅在有明确需求绕过设备检测时才使用 "},{"type":"element","tag":"code","props":{"className":[]},"children":[{"type":"text","value":"'always'"}]},{"type":"text","value":"。"}]}]},{"type":"element","tag":"h2","props":{"id":"禁用边缘检测"},"children":[{"type":"text","value":"禁用边缘检测"}]},{"type":"element","tag":"p","props":{},"children":[{"type":"text","value":"默认情况下，指令会在滚动触达容器边界时将控制权交还浏览器，以支持 iOS 侧滑返回等原生手势。在全屏覆盖层场景（如横屏模式）下，这个行为是不需要的。设置 "},{"type":"element","tag":"code","props":{"className":[]},"children":[{"type":"text","value":"disableEdgeDetection: true"}]},{"type":"text","value":" 可保持指令的完全接管："}]},{"type":"element","tag":"pre","props":{"className":"language-vue shiki shiki-themes github-light github-dark","code":"<template>\n  <div v-table-touch-scroll=\"{ preset: 'element-plus', disableEdgeDetection: true }\">\n    <el-table :data=\"tableData\" />\n  </div>\n</template>\n","language":"vue","meta":"","style":""},"children":[{"type":"element","tag":"code","props":{"__ignoreMap":""},"children":[{"type":"element","tag":"span","props":{"class":"line","line":1},"children":[{"type":"element","tag":"span","props":{"style":"--shiki-default:#24292E;--shiki-dark:#E1E4E8"},"children":[{"type":"text","value":"<"}]},{"type":"element","tag":"span","props":{"style":"--shiki-default:#22863A;--shiki-dark:#85E89D"},"children":[{"type":"text","value":"template"}]},{"type":"element","tag":"span","props":{"style":"--shiki-default:#24292E;--shiki-dark:#E1E4E8"},"children":[{"type":"text","value":">\n"}]}]},{"type":"element","tag":"span","props":{"class":"line","line":2},"children":[{"type":"element","tag":"span","props":{"style":"--shiki-default:#24292E;--shiki-dark:#E1E4E8"},"children":[{"type":"text","value":"  <"}]},{"type":"element","tag":"span","props":{"style":"--shiki-default:#22863A;--shiki-dark:#85E89D"},"children":[{"type":"text","value":"div"}]},{"type":"element","tag":"span","props":{"style":"--shiki-default:#6F42C1;--shiki-dark:#B392F0"},"children":[{"type":"text","value":" v-table-touch-scroll"}]},{"type":"element","tag":"span","props":{"style":"--shiki-default:#24292E;--shiki-dark:#E1E4E8"},"children":[{"type":"text","value":"="}]},{"type":"element","tag":"span","props":{"style":"--shiki-default:#032F62;--shiki-dark:#9ECBFF"},"children":[{"type":"text","value":"\"{ preset: 'element-plus', disableEdgeDetection: true }\""}]},{"type":"element","tag":"span","props":{"style":"--shiki-default:#24292E;--shiki-dark:#E1E4E8"},"children":[{"type":"text","value":">\n"}]}]},{"type":"element","tag":"span","props":{"class":"line","line":3},"children":[{"type":"element","tag":"span","props":{"style":"--shiki-default:#24292E;--shiki-dark:#E1E4E8"},"children":[{"type":"text","value":"    <"}]},{"type":"element","tag":"span","props":{"style":"--shiki-default:#22863A;--shiki-dark:#85E89D"},"children":[{"type":"text","value":"el-table"}]},{"type":"element","tag":"span","props":{"style":"--shiki-default:#6F42C1;--shiki-dark:#B392F0"},"children":[{"type":"text","value":" :data"}]},{"type":"element","tag":"span","props":{"style":"--shiki-default:#24292E;--shiki-dark:#E1E4E8"},"children":[{"type":"text","value":"="}]},{"type":"element","tag":"span","props":{"style":"--shiki-default:#032F62;--shiki-dark:#9ECBFF"},"children":[{"type":"text","value":"\"tableData\""}]},{"type":"element","tag":"span","props":{"style":"--shiki-default:#24292E;--shiki-dark:#E1E4E8"},"children":[{"type":"text","value":" />\n"}]}]},{"type":"element","tag":"span","props":{"class":"line","line":4},"children":[{"type":"element","tag":"span","props":{"style":"--shiki-default:#24292E;--shiki-dark:#E1E4E8"},"children":[{"type":"text","value":"  </"}]},{"type":"element","tag":"span","props":{"style":"--shiki-default:#22863A;--shiki-dark:#85E89D"},"children":[{"type":"text","value":"div"}]},{"type":"element","tag":"span","props":{"style":"--shiki-default:#24292E;--shiki-dark:#E1E4E8"},"children":[{"type":"text","value":">\n"}]}]},{"type":"element","tag":"span","props":{"class":"line","line":5},"children":[{"type":"element","tag":"span","props":{"style":"--shiki-default:#24292E;--shiki-dark:#E1E4E8"},"children":[{"type":"text","value":"</"}]},{"type":"element","tag":"span","props":{"style":"--shiki-default:#22863A;--shiki-dark:#85E89D"},"children":[{"type":"text","value":"template"}]},{"type":"element","tag":"span","props":{"style":"--shiki-default:#24292E;--shiki-dark:#E1E4E8"},"children":[{"type":"text","value":">\n"}]}]}]}]},{"type":"element","tag":"callout","props":{"icon":"lucide:triangle-alert","color":"amber"},"children":[{"type":"element","tag":"p","props":{},"children":[{"type":"text","value":"仅在表格处于全屏覆盖层或需要阻止浏览器原生边缘手势的场景下启用此选项。在常规页面布局中，边缘检测能提升用户体验（允许侧滑返回和外层滚动）。"}]}]},{"type":"element","tag":"h2","props":{"id":"css-旋转支持"},"children":[{"type":"text","value":"CSS 旋转支持"}]},{"type":"element","tag":"p","props":{},"children":[{"type":"text","value":"当通过 CSS "},{"type":"element","tag":"code","props":{"className":[]},"children":[{"type":"text","value":"transform: rotate()"}]},{"type":"text","value":" 模拟移动端横屏时，触摸坐标轴与元素逻辑轴不再对齐。"},{"type":"element","tag":"code","props":{"className":[]},"children":[{"type":"text","value":"rotation"}]},{"type":"text","value":" 参数会告知指令当前旋转角度，自动执行坐标逆变换："}]},{"type":"element","tag":"pre","props":{"className":"language-vue shiki shiki-themes github-light github-dark","code":"<template>\n  <div\n    v-table-touch-scroll=\"{ preset: 'element-plus', rotation: 90 }\"\n    class=\"landscape-container\"\n  >\n    <el-table :data=\"tableData\" />\n  </div>\n</template>\n\n<style scoped>\n.landscape-container {\n  transform: rotate(90deg);\n  transform-origin: top left;\n  width: 100vh;\n  height: 100vw;\n  translate: 100vw 0;\n}\n</style>\n","language":"vue","meta":"","style":""},"children":[{"type":"element","tag":"code","props":{"__ignoreMap":""},"children":[{"type":"element","tag":"span","props":{"class":"line","line":1},"children":[{"type":"element","tag":"span","props":{"style":"--shiki-default:#24292E;--shiki-dark:#E1E4E8"},"children":[{"type":"text","value":"<"}]},{"type":"element","tag":"span","props":{"style":"--shiki-default:#22863A;--shiki-dark:#85E89D"},"children":[{"type":"text","value":"template"}]},{"type":"element","tag":"span","props":{"style":"--shiki-default:#24292E;--shiki-dark:#E1E4E8"},"children":[{"type":"text","value":">\n"}]}]},{"type":"element","tag":"span","props":{"class":"line","line":2},"children":[{"type":"element","tag":"span","props":{"style":"--shiki-default:#24292E;--shiki-dark:#E1E4E8"},"children":[{"type":"text","value":"  <"}]},{"type":"element","tag":"span","props":{"style":"--shiki-default:#22863A;--shiki-dark:#85E89D"},"children":[{"type":"text","value":"div\n"}]}]},{"type":"element","tag":"span","props":{"class":"line","line":3},"children":[{"type":"element","tag":"span","props":{"style":"--shiki-default:#6F42C1;--shiki-dark:#B392F0"},"children":[{"type":"text","value":"    v-table-touch-scroll"}]},{"type":"element","tag":"span","props":{"style":"--shiki-default:#24292E;--shiki-dark:#E1E4E8"},"children":[{"type":"text","value":"="}]},{"type":"element","tag":"span","props":{"style":"--shiki-default:#032F62;--shiki-dark:#9ECBFF"},"children":[{"type":"text","value":"\"{ preset: 'element-plus', rotation: 90 }\"\n"}]}]},{"type":"element","tag":"span","props":{"class":"line","line":4},"children":[{"type":"element","tag":"span","props":{"style":"--shiki-default:#6F42C1;--shiki-dark:#B392F0"},"children":[{"type":"text","value":"    class"}]},{"type":"element","tag":"span","props":{"style":"--shiki-default:#24292E;--shiki-dark:#E1E4E8"},"children":[{"type":"text","value":"="}]},{"type":"element","tag":"span","props":{"style":"--shiki-default:#032F62;--shiki-dark:#9ECBFF"},"children":[{"type":"text","value":"\"landscape-container\"\n"}]}]},{"type":"element","tag":"span","props":{"class":"line","line":5},"children":[{"type":"element","tag":"span","props":{"style":"--shiki-default:#24292E;--shiki-dark:#E1E4E8"},"children":[{"type":"text","value":"  >\n"}]}]},{"type":"element","tag":"span","props":{"class":"line","line":6},"children":[{"type":"element","tag":"span","props":{"style":"--shiki-default:#24292E;--shiki-dark:#E1E4E8"},"children":[{"type":"text","value":"    <"}]},{"type":"element","tag":"span","props":{"style":"--shiki-default:#22863A;--shiki-dark:#85E89D"},"children":[{"type":"text","value":"el-table"}]},{"type":"element","tag":"span","props":{"style":"--shiki-default:#6F42C1;--shiki-dark:#B392F0"},"children":[{"type":"text","value":" :data"}]},{"type":"element","tag":"span","props":{"style":"--shiki-default:#24292E;--shiki-dark:#E1E4E8"},"children":[{"type":"text","value":"="}]},{"type":"element","tag":"span","props":{"style":"--shiki-default:#032F62;--shiki-dark:#9ECBFF"},"children":[{"type":"text","value":"\"tableData\""}]},{"type":"element","tag":"span","props":{"style":"--shiki-default:#24292E;--shiki-dark:#E1E4E8"},"children":[{"type":"text","value":" />\n"}]}]},{"type":"element","tag":"span","props":{"class":"line","line":7},"children":[{"type":"element","tag":"span","props":{"style":"--shiki-default:#24292E;--shiki-dark:#E1E4E8"},"children":[{"type":"text","value":"  </"}]},{"type":"element","tag":"span","props":{"style":"--shiki-default:#22863A;--shiki-dark:#85E89D"},"children":[{"type":"text","value":"div"}]},{"type":"element","tag":"span","props":{"style":"--shiki-default:#24292E;--shiki-dark:#E1E4E8"},"children":[{"type":"text","value":">\n"}]}]},{"type":"element","tag":"span","props":{"class":"line","line":8},"children":[{"type":"element","tag":"span","props":{"style":"--shiki-default:#24292E;--shiki-dark:#E1E4E8"},"children":[{"type":"text","value":"</"}]},{"type":"element","tag":"span","props":{"style":"--shiki-default:#22863A;--shiki-dark:#85E89D"},"children":[{"type":"text","value":"template"}]},{"type":"element","tag":"span","props":{"style":"--shiki-default:#24292E;--shiki-dark:#E1E4E8"},"children":[{"type":"text","value":">\n"}]}]},{"type":"element","tag":"span","props":{"class":"line","line":9},"children":[{"type":"element","tag":"span","props":{"emptyLinePlaceholder":true},"children":[{"type":"text","value":"\n"}]}]},{"type":"element","tag":"span","props":{"class":"line","line":10},"children":[{"type":"element","tag":"span","props":{"style":"--shiki-default:#24292E;--shiki-dark:#E1E4E8"},"children":[{"type":"text","value":"<"}]},{"type":"element","tag":"span","props":{"style":"--shiki-default:#22863A;--shiki-dark:#85E89D"},"children":[{"type":"text","value":"style"}]},{"type":"element","tag":"span","props":{"style":"--shiki-default:#6F42C1;--shiki-dark:#B392F0"},"children":[{"type":"text","value":" scoped"}]},{"type":"element","tag":"span","props":{"style":"--shiki-default:#24292E;--shiki-dark:#E1E4E8"},"children":[{"type":"text","value":">\n"}]}]},{"type":"element","tag":"span","props":{"class":"line","line":11},"children":[{"type":"element","tag":"span","props":{"style":"--shiki-default:#6F42C1;--shiki-dark:#B392F0"},"children":[{"type":"text","value":".landscape-container"}]},{"type":"element","tag":"span","props":{"style":"--shiki-default:#24292E;--shiki-dark:#E1E4E8"},"children":[{"type":"text","value":" {\n"}]}]},{"type":"element","tag":"span","props":{"class":"line","line":12},"children":[{"type":"element","tag":"span","props":{"style":"--shiki-default:#005CC5;--shiki-dark:#79B8FF"},"children":[{"type":"text","value":"  transform"}]},{"type":"element","tag":"span","props":{"style":"--shiki-default:#24292E;--shiki-dark:#E1E4E8"},"children":[{"type":"text","value":": "}]},{"type":"element","tag":"span","props":{"style":"--shiki-default:#005CC5;--shiki-dark:#79B8FF"},"children":[{"type":"text","value":"rotate"}]},{"type":"element","tag":"span","props":{"style":"--shiki-default:#24292E;--shiki-dark:#E1E4E8"},"children":[{"type":"text","value":"("}]},{"type":"element","tag":"span","props":{"style":"--shiki-default:#005CC5;--shiki-dark:#79B8FF"},"children":[{"type":"text","value":"90"}]},{"type":"element","tag":"span","props":{"style":"--shiki-default:#D73A49;--shiki-dark:#F97583"},"children":[{"type":"text","value":"deg"}]},{"type":"element","tag":"span","props":{"style":"--shiki-default:#24292E;--shiki-dark:#E1E4E8"},"children":[{"type":"text","value":");\n"}]}]},{"type":"element","tag":"span","props":{"class":"line","line":13},"children":[{"type":"element","tag":"span","props":{"style":"--shiki-default:#005CC5;--shiki-dark:#79B8FF"},"children":[{"type":"text","value":"  transform-origin"}]},{"type":"element","tag":"span","props":{"style":"--shiki-default:#24292E;--shiki-dark:#E1E4E8"},"children":[{"type":"text","value":": "}]},{"type":"element","tag":"span","props":{"style":"--shiki-default:#005CC5;--shiki-dark:#79B8FF"},"children":[{"type":"text","value":"top"}]},{"type":"element","tag":"span","props":{"style":"--shiki-default:#005CC5;--shiki-dark:#79B8FF"},"children":[{"type":"text","value":" left"}]},{"type":"element","tag":"span","props":{"style":"--shiki-default:#24292E;--shiki-dark:#E1E4E8"},"children":[{"type":"text","value":";\n"}]}]},{"type":"element","tag":"span","props":{"class":"line","line":14},"children":[{"type":"element","tag":"span","props":{"style":"--shiki-default:#005CC5;--shiki-dark:#79B8FF"},"children":[{"type":"text","value":"  width"}]},{"type":"element","tag":"span","props":{"style":"--shiki-default:#24292E;--shiki-dark:#E1E4E8"},"children":[{"type":"text","value":": "}]},{"type":"element","tag":"span","props":{"style":"--shiki-default:#005CC5;--shiki-dark:#79B8FF"},"children":[{"type":"text","value":"100"}]},{"type":"element","tag":"span","props":{"style":"--shiki-default:#D73A49;--shiki-dark:#F97583"},"children":[{"type":"text","value":"vh"}]},{"type":"element","tag":"span","props":{"style":"--shiki-default:#24292E;--shiki-dark:#E1E4E8"},"children":[{"type":"text","value":";\n"}]}]},{"type":"element","tag":"span","props":{"class":"line","line":15},"children":[{"type":"element","tag":"span","props":{"style":"--shiki-default:#005CC5;--shiki-dark:#79B8FF"},"children":[{"type":"text","value":"  height"}]},{"type":"element","tag":"span","props":{"style":"--shiki-default:#24292E;--shiki-dark:#E1E4E8"},"children":[{"type":"text","value":": "}]},{"type":"element","tag":"span","props":{"style":"--shiki-default:#005CC5;--shiki-dark:#79B8FF"},"children":[{"type":"text","value":"100"}]},{"type":"element","tag":"span","props":{"style":"--shiki-default:#D73A49;--shiki-dark:#F97583"},"children":[{"type":"text","value":"vw"}]},{"type":"element","tag":"span","props":{"style":"--shiki-default:#24292E;--shiki-dark:#E1E4E8"},"children":[{"type":"text","value":";\n"}]}]},{"type":"element","tag":"span","props":{"class":"line","line":16},"children":[{"type":"element","tag":"span","props":{"style":"--shiki-default:#005CC5;--shiki-dark:#79B8FF"},"children":[{"type":"text","value":"  translate"}]},{"type":"element","tag":"span","props":{"style":"--shiki-default:#24292E;--shiki-dark:#E1E4E8"},"children":[{"type":"text","value":": "}]},{"type":"element","tag":"span","props":{"style":"--shiki-default:#005CC5;--shiki-dark:#79B8FF"},"children":[{"type":"text","value":"100"}]},{"type":"element","tag":"span","props":{"style":"--shiki-default:#D73A49;--shiki-dark:#F97583"},"children":[{"type":"text","value":"vw"}]},{"type":"element","tag":"span","props":{"style":"--shiki-default:#005CC5;--shiki-dark:#79B8FF"},"children":[{"type":"text","value":" 0"}]},{"type":"element","tag":"span","props":{"style":"--shiki-default:#24292E;--shiki-dark:#E1E4E8"},"children":[{"type":"text","value":";\n"}]}]},{"type":"element","tag":"span","props":{"class":"line","line":17},"children":[{"type":"element","tag":"span","props":{"style":"--shiki-default:#24292E;--shiki-dark:#E1E4E8"},"children":[{"type":"text","value":"}\n"}]}]},{"type":"element","tag":"span","props":{"class":"line","line":18},"children":[{"type":"element","tag":"span","props":{"style":"--shiki-default:#24292E;--shiki-dark:#E1E4E8"},"children":[{"type":"text","value":"</"}]},{"type":"element","tag":"span","props":{"style":"--shiki-default:#22863A;--shiki-dark:#85E89D"},"children":[{"type":"text","value":"style"}]},{"type":"element","tag":"span","props":{"style":"--shiki-default:#24292E;--shiki-dark:#E1E4E8"},"children":[{"type":"text","value":">\n"}]}]}]}]},{"type":"element","tag":"p","props":{},"children":[{"type":"text","value":"支持的值："},{"type":"element","tag":"code","props":{"className":[]},"children":[{"type":"text","value":"0"}]},{"type":"text","value":"（默认）、"},{"type":"element","tag":"code","props":{"className":[]},"children":[{"type":"text","value":"90"}]},{"type":"text","value":"、"},{"type":"element","tag":"code","props":{"className":[]},"children":[{"type":"text","value":"-90"}]},{"type":"text","value":"、"},{"type":"element","tag":"code","props":{"className":[]},"children":[{"type":"text","value":"180"}]},{"type":"text","value":"。完整的横屏切换示例请查看"},{"type":"element","tag":"a","props":{"href":"/zh/landscape/landscape"},"children":[{"type":"text","value":"移动端横屏方案"}]},{"type":"text","value":"。"}]},{"type":"element","tag":"h2","props":{"id":"生命周期回调"},"children":[{"type":"text","value":"生命周期回调"}]},{"type":"element","tag":"pre","props":{"className":"language-vue shiki shiki-themes github-light github-dark","code":"<script setup lang=\"ts\">\nconst scrollOptions = {\n  preset: 'element-plus' as const,\n  onScrollStart: () => {\n    // 滚动开始：关闭浮层、记录开始时间等\n  },\n  onScrollEnd: () => {\n    // 滚动结束：触发埋点、加载更多数据等\n  },\n}\n</script>\n\n<template>\n  <div v-table-touch-scroll=\"scrollOptions\">\n    <el-table :data=\"tableData\" />\n  </div>\n</template>\n","language":"vue","meta":"","style":""},"children":[{"type":"element","tag":"code","props":{"__ignoreMap":""},"children":[{"type":"element","tag":"span","props":{"class":"line","line":1},"children":[{"type":"element","tag":"span","props":{"style":"--shiki-default:#24292E;--shiki-dark:#E1E4E8"},"children":[{"type":"text","value":"<"}]},{"type":"element","tag":"span","props":{"style":"--shiki-default:#22863A;--shiki-dark:#85E89D"},"children":[{"type":"text","value":"script"}]},{"type":"element","tag":"span","props":{"style":"--shiki-default:#6F42C1;--shiki-dark:#B392F0"},"children":[{"type":"text","value":" setup"}]},{"type":"element","tag":"span","props":{"style":"--shiki-default:#6F42C1;--shiki-dark:#B392F0"},"children":[{"type":"text","value":" lang"}]},{"type":"element","tag":"span","props":{"style":"--shiki-default:#24292E;--shiki-dark:#E1E4E8"},"children":[{"type":"text","value":"="}]},{"type":"element","tag":"span","props":{"style":"--shiki-default:#032F62;--shiki-dark:#9ECBFF"},"children":[{"type":"text","value":"\"ts\""}]},{"type":"element","tag":"span","props":{"style":"--shiki-default:#24292E;--shiki-dark:#E1E4E8"},"children":[{"type":"text","value":">\n"}]}]},{"type":"element","tag":"span","props":{"class":"line","line":2},"children":[{"type":"element","tag":"span","props":{"style":"--shiki-default:#D73A49;--shiki-dark:#F97583"},"children":[{"type":"text","value":"const"}]},{"type":"element","tag":"span","props":{"style":"--shiki-default:#005CC5;--shiki-dark:#79B8FF"},"children":[{"type":"text","value":" scrollOptions"}]},{"type":"element","tag":"span","props":{"style":"--shiki-default:#D73A49;--shiki-dark:#F97583"},"children":[{"type":"text","value":" ="}]},{"type":"element","tag":"span","props":{"style":"--shiki-default:#24292E;--shiki-dark:#E1E4E8"},"children":[{"type":"text","value":" {\n"}]}]},{"type":"element","tag":"span","props":{"class":"line","line":3},"children":[{"type":"element","tag":"span","props":{"style":"--shiki-default:#24292E;--shiki-dark:#E1E4E8"},"children":[{"type":"text","value":"  preset: "}]},{"type":"element","tag":"span","props":{"style":"--shiki-default:#032F62;--shiki-dark:#9ECBFF"},"children":[{"type":"text","value":"'element-plus'"}]},{"type":"element","tag":"span","props":{"style":"--shiki-default:#D73A49;--shiki-dark:#F97583"},"children":[{"type":"text","value":" as"}]},{"type":"element","tag":"span","props":{"style":"--shiki-default:#D73A49;--shiki-dark:#F97583"},"children":[{"type":"text","value":" const"}]},{"type":"element","tag":"span","props":{"style":"--shiki-default:#24292E;--shiki-dark:#E1E4E8"},"children":[{"type":"text","value":",\n"}]}]},{"type":"element","tag":"span","props":{"class":"line","line":4},"children":[{"type":"element","tag":"span","props":{"style":"--shiki-default:#6F42C1;--shiki-dark:#B392F0"},"children":[{"type":"text","value":"  onScrollStart"}]},{"type":"element","tag":"span","props":{"style":"--shiki-default:#24292E;--shiki-dark:#E1E4E8"},"children":[{"type":"text","value":": () "}]},{"type":"element","tag":"span","props":{"style":"--shiki-default:#D73A49;--shiki-dark:#F97583"},"children":[{"type":"text","value":"=>"}]},{"type":"element","tag":"span","props":{"style":"--shiki-default:#24292E;--shiki-dark:#E1E4E8"},"children":[{"type":"text","value":" {\n"}]}]},{"type":"element","tag":"span","props":{"class":"line","line":5},"children":[{"type":"element","tag":"span","props":{"style":"--shiki-default:#6A737D;--shiki-dark:#6A737D"},"children":[{"type":"text","value":"    // 滚动开始：关闭浮层、记录开始时间等\n"}]}]},{"type":"element","tag":"span","props":{"class":"line","line":6},"children":[{"type":"element","tag":"span","props":{"style":"--shiki-default:#24292E;--shiki-dark:#E1E4E8"},"children":[{"type":"text","value":"  },\n"}]}]},{"type":"element","tag":"span","props":{"class":"line","line":7},"children":[{"type":"element","tag":"span","props":{"style":"--shiki-default:#6F42C1;--shiki-dark:#B392F0"},"children":[{"type":"text","value":"  onScrollEnd"}]},{"type":"element","tag":"span","props":{"style":"--shiki-default:#24292E;--shiki-dark:#E1E4E8"},"children":[{"type":"text","value":": () "}]},{"type":"element","tag":"span","props":{"style":"--shiki-default:#D73A49;--shiki-dark:#F97583"},"children":[{"type":"text","value":"=>"}]},{"type":"element","tag":"span","props":{"style":"--shiki-default:#24292E;--shiki-dark:#E1E4E8"},"children":[{"type":"text","value":" {\n"}]}]},{"type":"element","tag":"span","props":{"class":"line","line":8},"children":[{"type":"element","tag":"span","props":{"style":"--shiki-default:#6A737D;--shiki-dark:#6A737D"},"children":[{"type":"text","value":"    // 滚动结束：触发埋点、加载更多数据等\n"}]}]},{"type":"element","tag":"span","props":{"class":"line","line":9},"children":[{"type":"element","tag":"span","props":{"style":"--shiki-default:#24292E;--shiki-dark:#E1E4E8"},"children":[{"type":"text","value":"  },\n"}]}]},{"type":"element","tag":"span","props":{"class":"line","line":10},"children":[{"type":"element","tag":"span","props":{"style":"--shiki-default:#24292E;--shiki-dark:#E1E4E8"},"children":[{"type":"text","value":"}\n"}]}]},{"type":"element","tag":"span","props":{"class":"line","line":11},"children":[{"type":"element","tag":"span","props":{"style":"--shiki-default:#24292E;--shiki-dark:#E1E4E8"},"children":[{"type":"text","value":"</"}]},{"type":"element","tag":"span","props":{"style":"--shiki-default:#22863A;--shiki-dark:#85E89D"},"children":[{"type":"text","value":"script"}]},{"type":"element","tag":"span","props":{"style":"--shiki-default:#24292E;--shiki-dark:#E1E4E8"},"children":[{"type":"text","value":">\n"}]}]},{"type":"element","tag":"span","props":{"class":"line","line":12},"children":[{"type":"element","tag":"span","props":{"emptyLinePlaceholder":true},"children":[{"type":"text","value":"\n"}]}]},{"type":"element","tag":"span","props":{"class":"line","line":13},"children":[{"type":"element","tag":"span","props":{"style":"--shiki-default:#24292E;--shiki-dark:#E1E4E8"},"children":[{"type":"text","value":"<"}]},{"type":"element","tag":"span","props":{"style":"--shiki-default:#22863A;--shiki-dark:#85E89D"},"children":[{"type":"text","value":"template"}]},{"type":"element","tag":"span","props":{"style":"--shiki-default:#24292E;--shiki-dark:#E1E4E8"},"children":[{"type":"text","value":">\n"}]}]},{"type":"element","tag":"span","props":{"class":"line","line":14},"children":[{"type":"element","tag":"span","props":{"style":"--shiki-default:#24292E;--shiki-dark:#E1E4E8"},"children":[{"type":"text","value":"  <"}]},{"type":"element","tag":"span","props":{"style":"--shiki-default:#22863A;--shiki-dark:#85E89D"},"children":[{"type":"text","value":"div"}]},{"type":"element","tag":"span","props":{"style":"--shiki-default:#6F42C1;--shiki-dark:#B392F0"},"children":[{"type":"text","value":" v-table-touch-scroll"}]},{"type":"element","tag":"span","props":{"style":"--shiki-default:#24292E;--shiki-dark:#E1E4E8"},"children":[{"type":"text","value":"="}]},{"type":"element","tag":"span","props":{"style":"--shiki-default:#032F62;--shiki-dark:#9ECBFF"},"children":[{"type":"text","value":"\"scrollOptions\""}]},{"type":"element","tag":"span","props":{"style":"--shiki-default:#24292E;--shiki-dark:#E1E4E8"},"children":[{"type":"text","value":">\n"}]}]},{"type":"element","tag":"span","props":{"class":"line","line":15},"children":[{"type":"element","tag":"span","props":{"style":"--shiki-default:#24292E;--shiki-dark:#E1E4E8"},"children":[{"type":"text","value":"    <"}]},{"type":"element","tag":"span","props":{"style":"--shiki-default:#22863A;--shiki-dark:#85E89D"},"children":[{"type":"text","value":"el-table"}]},{"type":"element","tag":"span","props":{"style":"--shiki-default:#6F42C1;--shiki-dark:#B392F0"},"children":[{"type":"text","value":" :data"}]},{"type":"element","tag":"span","props":{"style":"--shiki-default:#24292E;--shiki-dark:#E1E4E8"},"children":[{"type":"text","value":"="}]},{"type":"element","tag":"span","props":{"style":"--shiki-default:#032F62;--shiki-dark:#9ECBFF"},"children":[{"type":"text","value":"\"tableData\""}]},{"type":"element","tag":"span","props":{"style":"--shiki-default:#24292E;--shiki-dark:#E1E4E8"},"children":[{"type":"text","value":" />\n"}]}]},{"type":"element","tag":"span","props":{"class":"line","line":16},"children":[{"type":"element","tag":"span","props":{"style":"--shiki-default:#24292E;--shiki-dark:#E1E4E8"},"children":[{"type":"text","value":"  </"}]},{"type":"element","tag":"span","props":{"style":"--shiki-default:#22863A;--shiki-dark:#85E89D"},"children":[{"type":"text","value":"div"}]},{"type":"element","tag":"span","props":{"style":"--shiki-default:#24292E;--shiki-dark:#E1E4E8"},"children":[{"type":"text","value":">\n"}]}]},{"type":"element","tag":"span","props":{"class":"line","line":17},"children":[{"type":"element","tag":"span","props":{"style":"--shiki-default:#24292E;--shiki-dark:#E1E4E8"},"children":[{"type":"text","value":"</"}]},{"type":"element","tag":"span","props":{"style":"--shiki-default:#22863A;--shiki-dark:#85E89D"},"children":[{"type":"text","value":"template"}]},{"type":"element","tag":"span","props":{"style":"--shiki-default:#24292E;--shiki-dark:#E1E4E8"},"children":[{"type":"text","value":">\n"}]}]}]}]},{"type":"element","tag":"style","props":{},"children":[{"type":"text","value":"html .default .shiki span {color: var(--shiki-default);background: var(--shiki-default-bg);font-style: var(--shiki-default-font-style);font-weight: var(--shiki-default-font-weight);text-decoration: var(--shiki-default-text-decoration);}html .shiki span {color: var(--shiki-default);background: var(--shiki-default-bg);font-style: var(--shiki-default-font-style);font-weight: var(--shiki-default-font-weight);text-decoration: var(--shiki-default-text-decoration);}html .dark .shiki span {color: var(--shiki-dark);background: var(--shiki-dark-bg);font-style: var(--shiki-dark-font-style);font-weight: var(--shiki-dark-font-weight);text-decoration: var(--shiki-dark-text-decoration);}html.dark .shiki span {color: var(--shiki-dark);background: var(--shiki-dark-bg);font-style: var(--shiki-dark-font-style);font-weight: var(--shiki-dark-font-weight);text-decoration: var(--shiki-dark-text-decoration);}"}]}],"toc":{"title":"","searchDepth":2,"depth":2,"links":[{"id":"安装","depth":2,"text":"安装"},{"id":"全局注册","depth":2,"text":"全局注册"},{"id":"局部注册","depth":2,"text":"局部注册"},{"id":"在模板中使用","depth":2,"text":"在模板中使用"},{"id":"使用-ui-库预设","depth":2,"text":"使用 UI 库预设"},{"id":"使用自定义选择器","depth":2,"text":"使用自定义选择器"},{"id":"自定义物理参数","depth":2,"text":"自定义物理参数"},{"id":"动态控制","depth":2,"text":"动态控制"},{"id":"设备检测模式","depth":2,"text":"设备检测模式"},{"id":"禁用边缘检测","depth":2,"text":"禁用边缘检测"},{"id":"css-旋转支持","depth":2,"text":"CSS 旋转支持"},{"id":"生命周期回调","depth":2,"text":"生命周期回调"}]}},"_type":"markdown","_id":"content:zh:1.guide:2.configuration.md","_source":"content","_file":"zh/1.guide/2.configuration.md","_stem":"zh/1.guide/2.configuration","_extension":"md"}